{
  "schema": [
    {
      "name": "DirectType",
      "type": 1
    },
    {
      "name": "DirectFrm",
      "type": 1
    },
    {
      "name": "CamType",
      "type": 1
    },
    {
      "name": "CamAngle",
      "type": 1
    }
  ],
  "rows": [
    {
      "$id": 1,
      "DirectType": 1,
      "DirectFrm": 4,
      "CamType": 2,
      "CamAngle": 5
    },
    {
      "$id": 2,
      "DirectType": 1,
      "DirectFrm": 6,
      "CamType": 3,
      "CamAngle": 10
    },
    {
      "$id": 3,
      "DirectType": 1,
      "DirectFrm": 6,
      "CamType": 1,
      "CamAngle": 10
    },
    {
      "$id": 4,
      "DirectType": 1,
      "DirectFrm": 6,
      "CamType": 9,
      "CamAngle": 10
    },
    {
      "$id": 5,
      "DirectType": 1,
      "DirectFrm": 6,
      "CamType": 10,
      "CamAngle": 10
    },
    {
      "$id": 6,
      "DirectType": 1,
      "DirectFrm": 6,
      "CamType": 15,
      "CamAngle": 10
    },
    {
      "$id": 7,
      "DirectType": 1,
      "DirectFrm": 6,
      "CamType": 16,
      "CamAngle": 10
    },
    {
      "$id": 8,
      "DirectType": 1,
      "DirectFrm": 6,
      "CamType": 13,
      "CamAngle": 10
    },
    {
      "$id": 9,
      "DirectType": 1,
      "DirectFrm": 15,
      "CamType": 4,
      "CamAngle": 15
    },
    {
      "$id": 10,
      "DirectType": 1,
      "DirectFrm": 12,
      "CamType": 5,
      "CamAngle": 12
    },
    {
      "$id": 11,
      "DirectType": 1,
      "DirectFrm": 15,
      "CamType": 6,
      "CamAngle": 12
    },
    {
      "$id": 12,
      "DirectType": 1,
      "DirectFrm": 10,
      "CamType": 7,
      "CamAngle": 10
    },
    {
      "$id": 13,
      "DirectType": 1,
      "DirectFrm": 12,
      "CamType": 8,
      "CamAngle": 11
    },
    {
      "$id": 14,
      "DirectType": 0,
      "DirectFrm": 0,
      "CamType": 1,
      "CamAngle": 0
    },
    {
      "$id": 15,
      "DirectType": 0,
      "DirectFrm": 15,
      "CamType": 5,
      "CamAngle": 12
    },
    {
      "$id": 16,
      "DirectType": 1,
      "DirectFrm": 3,
      "CamType": 0,
      "CamAngle": 0
    },
    {
      "$id": 17,
      "DirectType": 1,
      "DirectFrm": 2,
      "CamType": 2,
      "CamAngle": 3
    },
    {
      "$id": 18,
      "DirectType": 1,
      "DirectFrm": 8,
      "CamType": 8,
      "CamAngle": 11
    }
  ]
}