{
  "schema": [
    {
      "name": "Flag",
      "type": 1,
      "flags": [
        {
          "label": "common",
          "mask": 1,
          "index": 0
        }
      ]
    },
    {
      "name": "KizunaBase",
      "type": 1
    },
    {
      "name": "VoiceID",
      "type": 1
    },
    {
      "name": "BLC_A",
      "type": 1
    },
    {
      "name": "BLC_PARAM_A",
      "type": 2
    },
    {
      "name": "BLC_B",
      "type": 1
    },
    {
      "name": "BLC_PARAM_B",
      "type": 2
    },
    {
      "name": "BLC_C",
      "type": 2
    },
    {
      "name": "BLC_D",
      "type": 2
    },
    {
      "name": "Custom01",
      "type": 1
    },
    {
      "name": "CustomParam01",
      "type": 1
    },
    {
      "name": "Custom02",
      "type": 1
    },
    {
      "name": "CustomParam02",
      "type": 1
    },
    {
      "name": "Custom03",
      "type": 1
    },
    {
      "name": "CustomParam03",
      "type": 1
    }
  ],
  "rows": [
    {
      "$id": 1,
      "Flag": {
        "common": 0
      },
      "KizunaBase": 1,
      "VoiceID": 0,
      "BLC_A": 7,
      "BLC_PARAM_A": 1,
      "BLC_B": 1,
      "BLC_PARAM_B": 0,
      "BLC_C": 1009,
      "BLC_D": 1002,
      "Custom01": 7,
      "CustomParam01": 0,
      "Custom02": 15,
      "CustomParam02": 0,
      "Custom03": 14,
      "CustomParam03": 0
    },
    {
      "$id": 2,
      "Flag": {
        "common": 0
      },
      "KizunaBase": 2,
      "VoiceID": 0,
      "BLC_A": 1,
      "BLC_PARAM_A": 0,
      "BLC_B": 8,
      "BLC_PARAM_B": 0,
      "BLC_C": 1011,
      "BLC_D": 1001,
      "Custom01": 8,
      "CustomParam01": 4,
      "Custom02": 6,
      "CustomParam02": 3,
      "Custom03": 2,
      "CustomParam03": 0
    },
    {
      "$id": 3,
      "Flag": {
        "common": 0
      },
      "KizunaBase": 3,
      "VoiceID": 0,
      "BLC_A": 8,
      "BLC_PARAM_A": 0,
      "BLC_B": 7,
      "BLC_PARAM_B": 1,
      "BLC_C": 0,
      "BLC_D": 0,
      "Custom01": 16,
      "CustomParam01": 0,
      "Custom02": 4,
      "CustomParam02": 0,
      "Custom03": 8,
      "CustomParam03": 4
    },
    {
      "$id": 4,
      "Flag": {
        "common": 0
      },
      "KizunaBase": 4,
      "VoiceID": 0,
      "BLC_A": 3,
      "BLC_PARAM_A": 0,
      "BLC_B": 4,
      "BLC_PARAM_B": 2,
      "BLC_C": 1011,
      "BLC_D": 1008,
      "Custom01": 1,
      "CustomParam01": 0,
      "Custom02": 2,
      "CustomParam02": 0,
      "Custom03": 3,
      "CustomParam03": 0
    },
    {
      "$id": 5,
      "Flag": {
        "common": 0
      },
      "KizunaBase": 5,
      "VoiceID": 0,
      "BLC_A": 2,
      "BLC_PARAM_A": 0,
      "BLC_B": 7,
      "BLC_PARAM_B": 2,
      "BLC_C": 1006,
      "BLC_D": 1007,
      "Custom01": 1,
      "CustomParam01": 0,
      "Custom02": 5,
      "CustomParam02": 0,
      "Custom03": 8,
      "CustomParam03": 4
    },
    {
      "$id": 6,
      "Flag": {
        "common": 0
      },
      "KizunaBase": 6,
      "VoiceID": 0,
      "BLC_A": 8,
      "BLC_PARAM_A": 0,
      "BLC_B": 1,
      "BLC_PARAM_B": 0,
      "BLC_C": 1005,
      "BLC_D": 1007,
      "Custom01": 6,
      "CustomParam01": 3,
      "Custom02": 5,
      "CustomParam02": 0,
      "Custom03": 11,
      "CustomParam03": 4
    },
    {
      "$id": 7,
      "Flag": {
        "common": 0
      },
      "KizunaBase": 7,
      "VoiceID": 0,
      "BLC_A": 8,
      "BLC_PARAM_A": 0,
      "BLC_B": 3,
      "BLC_PARAM_B": 5,
      "BLC_C": 1005,
      "BLC_D": 1006,
      "Custom01": 16,
      "CustomParam01": 0,
      "Custom02": 13,
      "CustomParam02": 0,
      "Custom03": 9,
      "CustomParam03": 0
    },
    {
      "$id": 8,
      "Flag": {
        "common": 0
      },
      "KizunaBase": 8,
      "VoiceID": 0,
      "BLC_A": 3,
      "BLC_PARAM_A": 2,
      "BLC_B": 4,
      "BLC_PARAM_B": 1,
      "BLC_C": 1001,
      "BLC_D": 1034,
      "Custom01": 6,
      "CustomParam01": 3,
      "Custom02": 7,
      "CustomParam02": 0,
      "Custom03": 12,
      "CustomParam03": 2
    },
    {
      "$id": 9,
      "Flag": {
        "common": 0
      },
      "KizunaBase": 9,
      "VoiceID": 0,
      "BLC_A": 4,
      "BLC_PARAM_A": 1,
      "BLC_B": 4,
      "BLC_PARAM_B": 6,
      "BLC_C": 1001,
      "BLC_D": 1014,
      "Custom01": 5,
      "CustomParam01": 0,
      "Custom02": 6,
      "CustomParam02": 3,
      "Custom03": 7,
      "CustomParam03": 0
    },
    {
      "$id": 10,
      "Flag": {
        "common": 0
      },
      "KizunaBase": 10,
      "VoiceID": 0,
      "BLC_A": 4,
      "BLC_PARAM_A": 1,
      "BLC_B": 4,
      "BLC_PARAM_B": 3,
      "BLC_C": 1036,
      "BLC_D": 1002,
      "Custom01": 16,
      "CustomParam01": 0,
      "Custom02": 9,
      "CustomParam02": 0,
      "Custom03": 11,
      "CustomParam03": 3
    },
    {
      "$id": 11,
      "Flag": {
        "common": 0
      },
      "KizunaBase": 11,
      "VoiceID": 0,
      "BLC_A": 6,
      "BLC_PARAM_A": 30,
      "BLC_B": 2,
      "BLC_PARAM_B": 0,
      "BLC_C": 1001,
      "BLC_D": 1004,
      "Custom01": 1,
      "CustomParam01": 0,
      "Custom02": 2,
      "CustomParam02": 0,
      "Custom03": 3,
      "CustomParam03": 0
    },
    {
      "$id": 12,
      "Flag": {
        "common": 0
      },
      "KizunaBase": 12,
      "VoiceID": 0,
      "BLC_A": 0,
      "BLC_PARAM_A": 0,
      "BLC_B": 0,
      "BLC_PARAM_B": 0,
      "BLC_C": 0,
      "BLC_D": 0,
      "Custom01": 0,
      "CustomParam01": 0,
      "Custom02": 0,
      "CustomParam02": 0,
      "Custom03": 0,
      "CustomParam03": 0
    },
    {
      "$id": 13,
      "Flag": {
        "common": 0
      },
      "KizunaBase": 13,
      "VoiceID": 0,
      "BLC_A": 0,
      "BLC_PARAM_A": 0,
      "BLC_B": 0,
      "BLC_PARAM_B": 0,
      "BLC_C": 0,
      "BLC_D": 0,
      "Custom01": 0,
      "CustomParam01": 0,
      "Custom02": 0,
      "CustomParam02": 0,
      "Custom03": 0,
      "CustomParam03": 0
    },
    {
      "$id": 14,
      "Flag": {
        "common": 0
      },
      "KizunaBase": 14,
      "VoiceID": 0,
      "BLC_A": 2,
      "BLC_PARAM_A": 0,
      "BLC_B": 6,
      "BLC_PARAM_B": 30,
      "BLC_C": 1009,
      "BLC_D": 1001,
      "Custom01": 6,
      "CustomParam01": 3,
      "Custom02": 5,
      "CustomParam02": 0,
      "Custom03": 2,
      "CustomParam03": 0
    },
    {
      "$id": 15,
      "Flag": {
        "common": 0
      },
      "KizunaBase": 15,
      "VoiceID": 0,
      "BLC_A": 2,
      "BLC_PARAM_A": 0,
      "BLC_B": 6,
      "BLC_PARAM_B": 30,
      "BLC_C": 1010,
      "BLC_D": 1001,
      "Custom01": 5,
      "CustomParam01": 0,
      "Custom02": 11,
      "CustomParam02": 2,
      "Custom03": 15,
      "CustomParam03": 0
    },
    {
      "$id": 16,
      "Flag": {
        "common": 0
      },
      "KizunaBase": 16,
      "VoiceID": 0,
      "BLC_A": 3,
      "BLC_PARAM_A": 2,
      "BLC_B": 1,
      "BLC_PARAM_B": 0,
      "BLC_C": 1036,
      "BLC_D": 1030,
      "Custom01": 4,
      "CustomParam01": 0,
      "Custom02": 12,
      "CustomParam02": 1,
      "Custom03": 9,
      "CustomParam03": 0
    },
    {
      "$id": 17,
      "Flag": {
        "common": 0
      },
      "KizunaBase": 17,
      "VoiceID": 0,
      "BLC_A": 1,
      "BLC_PARAM_A": 0,
      "BLC_B": 2,
      "BLC_PARAM_B": 0,
      "BLC_C": 1040,
      "BLC_D": 1037,
      "Custom01": 5,
      "CustomParam01": 0,
      "Custom02": 7,
      "CustomParam02": 0,
      "Custom03": 6,
      "CustomParam03": 3
    },
    {
      "$id": 18,
      "Flag": {
        "common": 0
      },
      "KizunaBase": 20,
      "VoiceID": 0,
      "BLC_A": 1,
      "BLC_PARAM_A": 0,
      "BLC_B": 2,
      "BLC_PARAM_B": 0,
      "BLC_C": 1015,
      "BLC_D": 1035,
      "Custom01": 15,
      "CustomParam01": 0,
      "Custom02": 13,
      "CustomParam02": 0,
      "Custom03": 12,
      "CustomParam03": 2
    },
    {
      "$id": 19,
      "Flag": {
        "common": 0
      },
      "KizunaBase": 22,
      "VoiceID": 0,
      "BLC_A": 3,
      "BLC_PARAM_A": 1,
      "BLC_B": 6,
      "BLC_PARAM_B": 30,
      "BLC_C": 1027,
      "BLC_D": 1032,
      "Custom01": 1,
      "CustomParam01": 0,
      "Custom02": 7,
      "CustomParam02": 0,
      "Custom03": 8,
      "CustomParam03": 4
    },
    {
      "$id": 20,
      "Flag": {
        "common": 0
      },
      "KizunaBase": 21,
      "VoiceID": 0,
      "BLC_A": 2,
      "BLC_PARAM_A": 0,
      "BLC_B": 3,
      "BLC_PARAM_B": 0,
      "BLC_C": 1031,
      "BLC_D": 1032,
      "Custom01": 3,
      "CustomParam01": 0,
      "Custom02": 14,
      "CustomParam02": 0,
      "Custom03": 11,
      "CustomParam03": 1
    },
    {
      "$id": 21,
      "Flag": {
        "common": 0
      },
      "KizunaBase": 38,
      "VoiceID": 0,
      "BLC_A": 2,
      "BLC_PARAM_A": 0,
      "BLC_B": 3,
      "BLC_PARAM_B": 1,
      "BLC_C": 1027,
      "BLC_D": 1029,
      "Custom01": 13,
      "CustomParam01": 0,
      "Custom02": 14,
      "CustomParam02": 0,
      "Custom03": 15,
      "CustomParam03": 0
    },
    {
      "$id": 22,
      "Flag": {
        "common": 0
      },
      "KizunaBase": 23,
      "VoiceID": 0,
      "BLC_A": 7,
      "BLC_PARAM_A": 2,
      "BLC_B": 8,
      "BLC_PARAM_B": 0,
      "BLC_C": 1028,
      "BLC_D": 1001,
      "Custom01": 5,
      "CustomParam01": 0,
      "Custom02": 8,
      "CustomParam02": 4,
      "Custom03": 11,
      "CustomParam03": 2
    },
    {
      "$id": 23,
      "Flag": {
        "common": 0
      },
      "KizunaBase": 24,
      "VoiceID": 0,
      "BLC_A": 7,
      "BLC_PARAM_A": 1,
      "BLC_B": 3,
      "BLC_PARAM_B": 1,
      "BLC_C": 1026,
      "BLC_D": 1025,
      "Custom01": 1,
      "CustomParam01": 0,
      "Custom02": 10,
      "CustomParam02": 0,
      "Custom03": 16,
      "CustomParam03": 0
    },
    {
      "$id": 24,
      "Flag": {
        "common": 0
      },
      "KizunaBase": 25,
      "VoiceID": 0,
      "BLC_A": 2,
      "BLC_PARAM_A": 0,
      "BLC_B": 6,
      "BLC_PARAM_B": 30,
      "BLC_C": 1024,
      "BLC_D": 1017,
      "Custom01": 6,
      "CustomParam01": 3,
      "Custom02": 5,
      "CustomParam02": 0,
      "Custom03": 13,
      "CustomParam03": 0
    },
    {
      "$id": 25,
      "Flag": {
        "common": 0
      },
      "KizunaBase": 26,
      "VoiceID": 0,
      "BLC_A": 1,
      "BLC_PARAM_A": 0,
      "BLC_B": 3,
      "BLC_PARAM_B": 4,
      "BLC_C": 1015,
      "BLC_D": 1014,
      "Custom01": 1,
      "CustomParam01": 0,
      "Custom02": 10,
      "CustomParam02": 0,
      "Custom03": 11,
      "CustomParam03": 1
    },
    {
      "$id": 26,
      "Flag": {
        "common": 0
      },
      "KizunaBase": 27,
      "VoiceID": 0,
      "BLC_A": 6,
      "BLC_PARAM_A": 30,
      "BLC_B": 3,
      "BLC_PARAM_B": 4,
      "BLC_C": 1028,
      "BLC_D": 1021,
      "Custom01": 9,
      "CustomParam01": 0,
      "Custom02": 12,
      "CustomParam02": 3,
      "Custom03": 2,
      "CustomParam03": 0
    },
    {
      "$id": 27,
      "Flag": {
        "common": 0
      },
      "KizunaBase": 28,
      "VoiceID": 0,
      "BLC_A": 3,
      "BLC_PARAM_A": 2,
      "BLC_B": 6,
      "BLC_PARAM_B": 30,
      "BLC_C": 1038,
      "BLC_D": 1023,
      "Custom01": 4,
      "CustomParam01": 0,
      "Custom02": 8,
      "CustomParam02": 4,
      "Custom03": 3,
      "CustomParam03": 0
    },
    {
      "$id": 28,
      "Flag": {
        "common": 0
      },
      "KizunaBase": 29,
      "VoiceID": 0,
      "BLC_A": 6,
      "BLC_PARAM_A": 30,
      "BLC_B": 3,
      "BLC_PARAM_B": 7,
      "BLC_C": 1035,
      "BLC_D": 1016,
      "Custom01": 3,
      "CustomParam01": 0,
      "Custom02": 1,
      "CustomParam02": 0,
      "Custom03": 9,
      "CustomParam03": 0
    },
    {
      "$id": 29,
      "Flag": {
        "common": 0
      },
      "KizunaBase": 30,
      "VoiceID": 0,
      "BLC_A": 3,
      "BLC_PARAM_A": 5,
      "BLC_B": 7,
      "BLC_PARAM_B": 2,
      "BLC_C": 1009,
      "BLC_D": 1028,
      "Custom01": 12,
      "CustomParam01": 4,
      "Custom02": 6,
      "CustomParam02": 3,
      "Custom03": 9,
      "CustomParam03": 0
    },
    {
      "$id": 30,
      "Flag": {
        "common": 0
      },
      "KizunaBase": 31,
      "VoiceID": 0,
      "BLC_A": 3,
      "BLC_PARAM_A": 0,
      "BLC_B": 3,
      "BLC_PARAM_B": 5,
      "BLC_C": 1019,
      "BLC_D": 1030,
      "Custom01": 1,
      "CustomParam01": 0,
      "Custom02": 13,
      "CustomParam02": 0,
      "Custom03": 3,
      "CustomParam03": 0
    },
    {
      "$id": 31,
      "Flag": {
        "common": 0
      },
      "KizunaBase": 32,
      "VoiceID": 0,
      "BLC_A": 1,
      "BLC_PARAM_A": 0,
      "BLC_B": 5,
      "BLC_PARAM_B": 1005,
      "BLC_C": 1029,
      "BLC_D": 1038,
      "Custom01": 15,
      "CustomParam01": 0,
      "Custom02": 16,
      "CustomParam02": 0,
      "Custom03": 9,
      "CustomParam03": 0
    },
    {
      "$id": 32,
      "Flag": {
        "common": 0
      },
      "KizunaBase": 33,
      "VoiceID": 0,
      "BLC_A": 6,
      "BLC_PARAM_A": 30,
      "BLC_B": 5,
      "BLC_PARAM_B": 1021,
      "BLC_C": 1034,
      "BLC_D": 1004,
      "Custom01": 14,
      "CustomParam01": 0,
      "Custom02": 4,
      "CustomParam02": 0,
      "Custom03": 10,
      "CustomParam03": 0
    },
    {
      "$id": 33,
      "Flag": {
        "common": 0
      },
      "KizunaBase": 34,
      "VoiceID": 0,
      "BLC_A": 3,
      "BLC_PARAM_A": 5,
      "BLC_B": 3,
      "BLC_PARAM_B": 3,
      "BLC_C": 1021,
      "BLC_D": 1037,
      "Custom01": 2,
      "CustomParam01": 0,
      "Custom02": 13,
      "CustomParam02": 0,
      "Custom03": 10,
      "CustomParam03": 0
    },
    {
      "$id": 34,
      "Flag": {
        "common": 0
      },
      "KizunaBase": 35,
      "VoiceID": 0,
      "BLC_A": 3,
      "BLC_PARAM_A": 5,
      "BLC_B": 5,
      "BLC_PARAM_B": 1038,
      "BLC_C": 1010,
      "BLC_D": 1036,
      "Custom01": 8,
      "CustomParam01": 4,
      "Custom02": 5,
      "CustomParam02": 0,
      "Custom03": 9,
      "CustomParam03": 0
    },
    {
      "$id": 35,
      "Flag": {
        "common": 0
      },
      "KizunaBase": 36,
      "VoiceID": 0,
      "BLC_A": 8,
      "BLC_PARAM_A": 0,
      "BLC_B": 3,
      "BLC_PARAM_B": 6,
      "BLC_C": 1039,
      "BLC_D": 1040,
      "Custom01": 7,
      "CustomParam01": 0,
      "Custom02": 1,
      "CustomParam02": 0,
      "Custom03": 16,
      "CustomParam03": 0
    },
    {
      "$id": 36,
      "Flag": {
        "common": 0
      },
      "KizunaBase": 37,
      "VoiceID": 0,
      "BLC_A": 7,
      "BLC_PARAM_A": 2,
      "BLC_B": 3,
      "BLC_PARAM_B": 2,
      "BLC_C": 1033,
      "BLC_D": 1008,
      "Custom01": 1,
      "CustomParam01": 0,
      "Custom02": 4,
      "CustomParam02": 0,
      "Custom03": 6,
      "CustomParam03": 3
    },
    {
      "$id": 37,
      "Flag": {
        "common": 0
      },
      "KizunaBase": 39,
      "VoiceID": 0,
      "BLC_A": 7,
      "BLC_PARAM_A": 2,
      "BLC_B": 8,
      "BLC_PARAM_B": 0,
      "BLC_C": 1002,
      "BLC_D": 1001,
      "Custom01": 2,
      "CustomParam01": 0,
      "Custom02": 8,
      "CustomParam02": 4,
      "Custom03": 9,
      "CustomParam03": 0
    },
    {
      "$id": 38,
      "Flag": {
        "common": 0
      },
      "KizunaBase": 40,
      "VoiceID": 0,
      "BLC_A": 6,
      "BLC_PARAM_A": 30,
      "BLC_B": 5,
      "BLC_PARAM_B": 1016,
      "BLC_C": 1039,
      "BLC_D": 1017,
      "Custom01": 14,
      "CustomParam01": 0,
      "Custom02": 2,
      "CustomParam02": 0,
      "Custom03": 16,
      "CustomParam03": 0
    },
    {
      "$id": 39,
      "Flag": {
        "common": 0
      },
      "KizunaBase": 41,
      "VoiceID": 0,
      "BLC_A": 1,
      "BLC_PARAM_A": 0,
      "BLC_B": 2,
      "BLC_PARAM_B": 0,
      "BLC_C": 1020,
      "BLC_D": 1026,
      "Custom01": 3,
      "CustomParam01": 0,
      "Custom02": 4,
      "CustomParam02": 0,
      "Custom03": 14,
      "CustomParam03": 0
    },
    {
      "$id": 40,
      "Flag": {
        "common": 0
      },
      "KizunaBase": 18,
      "VoiceID": 0,
      "BLC_A": 1,
      "BLC_PARAM_A": 0,
      "BLC_B": 8,
      "BLC_PARAM_B": 0,
      "BLC_C": 1022,
      "BLC_D": 1033,
      "Custom01": 13,
      "CustomParam01": 0,
      "Custom02": 8,
      "CustomParam02": 4,
      "Custom03": 12,
      "CustomParam03": 4
    },
    {
      "$id": 41,
      "Flag": {
        "common": 0
      },
      "KizunaBase": 19,
      "VoiceID": 0,
      "BLC_A": 3,
      "BLC_PARAM_A": 1,
      "BLC_B": 7,
      "BLC_PARAM_B": 1,
      "BLC_C": 1018,
      "BLC_D": 1041,
      "Custom01": 1,
      "CustomParam01": 0,
      "Custom02": 13,
      "CustomParam02": 0,
      "Custom03": 16,
      "CustomParam03": 0
    },
    {
      "$id": 42,
      "Flag": {
        "common": 0
      },
      "KizunaBase": 42,
      "VoiceID": 0,
      "BLC_A": 1,
      "BLC_PARAM_A": 0,
      "BLC_B": 8,
      "BLC_PARAM_B": 0,
      "BLC_C": 1046,
      "BLC_D": 1047,
      "Custom01": 2,
      "CustomParam01": 0,
      "Custom02": 11,
      "CustomParam02": 3,
      "Custom03": 7,
      "CustomParam03": 0
    },
    {
      "$id": 43,
      "Flag": {
        "common": 0
      },
      "KizunaBase": 43,
      "VoiceID": 0,
      "BLC_A": 2,
      "BLC_PARAM_A": 0,
      "BLC_B": 5,
      "BLC_PARAM_B": 1044,
      "BLC_C": 1044,
      "BLC_D": 1046,
      "Custom01": 8,
      "CustomParam01": 4,
      "Custom02": 10,
      "CustomParam02": 0,
      "Custom03": 11,
      "CustomParam03": 1
    },
    {
      "$id": 44,
      "Flag": {
        "common": 0
      },
      "KizunaBase": 44,
      "VoiceID": 0,
      "BLC_A": 1,
      "BLC_PARAM_A": 0,
      "BLC_B": 3,
      "BLC_PARAM_B": 4,
      "BLC_C": 1045,
      "BLC_D": 1001,
      "Custom01": 4,
      "CustomParam01": 0,
      "Custom02": 11,
      "CustomParam02": 1,
      "Custom03": 16,
      "CustomParam03": 0
    },
    {
      "$id": 45,
      "Flag": {
        "common": 0
      },
      "KizunaBase": 45,
      "VoiceID": 0,
      "BLC_A": 5,
      "BLC_PARAM_A": 1044,
      "BLC_B": 7,
      "BLC_PARAM_B": 1,
      "BLC_C": 1044,
      "BLC_D": 1048,
      "Custom01": 3,
      "CustomParam01": 0,
      "Custom02": 7,
      "CustomParam02": 0,
      "Custom03": 9,
      "CustomParam03": 0
    },
    {
      "$id": 46,
      "Flag": {
        "common": 0
      },
      "KizunaBase": 46,
      "VoiceID": 0,
      "BLC_A": 7,
      "BLC_PARAM_A": 2,
      "BLC_B": 8,
      "BLC_PARAM_B": 0,
      "BLC_C": 1043,
      "BLC_D": 1010,
      "Custom01": 7,
      "CustomParam01": 0,
      "Custom02": 10,
      "CustomParam02": 0,
      "Custom03": 12,
      "CustomParam03": 2
    },
    {
      "$id": 47,
      "Flag": {
        "common": 0
      },
      "KizunaBase": 47,
      "VoiceID": 0,
      "BLC_A": 5,
      "BLC_PARAM_A": 1048,
      "BLC_B": 8,
      "BLC_PARAM_B": 0,
      "BLC_C": 1001,
      "BLC_D": 1044,
      "Custom01": 7,
      "CustomParam01": 0,
      "Custom02": 9,
      "CustomParam02": 0,
      "Custom03": 11,
      "CustomParam03": 1
    },
    {
      "$id": 48,
      "Flag": {
        "common": 0
      },
      "KizunaBase": 48,
      "VoiceID": 0,
      "BLC_A": 8,
      "BLC_PARAM_A": 0,
      "BLC_B": 5,
      "BLC_PARAM_B": 1047,
      "BLC_C": 1016,
      "BLC_D": 1045,
      "Custom01": 1,
      "CustomParam01": 0,
      "Custom02": 9,
      "CustomParam02": 0,
      "Custom03": 11,
      "CustomParam03": 3
    },
    {
      "$id": 49,
      "Flag": {
        "common": 1
      },
      "KizunaBase": 49,
      "VoiceID": 61,
      "BLC_A": 1,
      "BLC_PARAM_A": 0,
      "BLC_B": 8,
      "BLC_PARAM_B": 0,
      "BLC_C": 0,
      "BLC_D": 0,
      "Custom01": 1,
      "CustomParam01": 0,
      "Custom02": 7,
      "CustomParam02": 0,
      "Custom03": 9,
      "CustomParam03": 0
    },
    {
      "$id": 50,
      "Flag": {
        "common": 1
      },
      "KizunaBase": 50,
      "VoiceID": 62,
      "BLC_A": 1,
      "BLC_PARAM_A": 0,
      "BLC_B": 8,
      "BLC_PARAM_B": 0,
      "BLC_C": 0,
      "BLC_D": 0,
      "Custom01": 1,
      "CustomParam01": 0,
      "Custom02": 7,
      "CustomParam02": 0,
      "Custom03": 9,
      "CustomParam03": 0
    },
    {
      "$id": 51,
      "Flag": {
        "common": 1
      },
      "KizunaBase": 51,
      "VoiceID": 63,
      "BLC_A": 1,
      "BLC_PARAM_A": 0,
      "BLC_B": 8,
      "BLC_PARAM_B": 0,
      "BLC_C": 0,
      "BLC_D": 0,
      "Custom01": 1,
      "CustomParam01": 0,
      "Custom02": 7,
      "CustomParam02": 0,
      "Custom03": 9,
      "CustomParam03": 0
    },
    {
      "$id": 52,
      "Flag": {
        "common": 1
      },
      "KizunaBase": 52,
      "VoiceID": 64,
      "BLC_A": 1,
      "BLC_PARAM_A": 0,
      "BLC_B": 8,
      "BLC_PARAM_B": 0,
      "BLC_C": 0,
      "BLC_D": 0,
      "Custom01": 1,
      "CustomParam01": 0,
      "Custom02": 7,
      "CustomParam02": 0,
      "Custom03": 9,
      "CustomParam03": 0
    },
    {
      "$id": 53,
      "Flag": {
        "common": 1
      },
      "KizunaBase": 53,
      "VoiceID": 65,
      "BLC_A": 1,
      "BLC_PARAM_A": 0,
      "BLC_B": 8,
      "BLC_PARAM_B": 0,
      "BLC_C": 0,
      "BLC_D": 0,
      "Custom01": 1,
      "CustomParam01": 0,
      "Custom02": 7,
      "CustomParam02": 0,
      "Custom03": 9,
      "CustomParam03": 0
    },
    {
      "$id": 54,
      "Flag": {
        "common": 1
      },
      "KizunaBase": 54,
      "VoiceID": 66,
      "BLC_A": 1,
      "BLC_PARAM_A": 0,
      "BLC_B": 8,
      "BLC_PARAM_B": 0,
      "BLC_C": 0,
      "BLC_D": 0,
      "Custom01": 1,
      "CustomParam01": 0,
      "Custom02": 7,
      "CustomParam02": 0,
      "Custom03": 9,
      "CustomParam03": 0
    },
    {
      "$id": 55,
      "Flag": {
        "common": 1
      },
      "KizunaBase": 55,
      "VoiceID": 67,
      "BLC_A": 1,
      "BLC_PARAM_A": 0,
      "BLC_B": 8,
      "BLC_PARAM_B": 0,
      "BLC_C": 0,
      "BLC_D": 0,
      "Custom01": 1,
      "CustomParam01": 0,
      "Custom02": 7,
      "CustomParam02": 0,
      "Custom03": 9,
      "CustomParam03": 0
    },
    {
      "$id": 56,
      "Flag": {
        "common": 1
      },
      "KizunaBase": 56,
      "VoiceID": 68,
      "BLC_A": 1,
      "BLC_PARAM_A": 0,
      "BLC_B": 8,
      "BLC_PARAM_B": 0,
      "BLC_C": 0,
      "BLC_D": 0,
      "Custom01": 1,
      "CustomParam01": 0,
      "Custom02": 7,
      "CustomParam02": 0,
      "Custom03": 9,
      "CustomParam03": 0
    },
    {
      "$id": 57,
      "Flag": {
        "common": 1
      },
      "KizunaBase": 57,
      "VoiceID": 69,
      "BLC_A": 1,
      "BLC_PARAM_A": 0,
      "BLC_B": 8,
      "BLC_PARAM_B": 0,
      "BLC_C": 0,
      "BLC_D": 0,
      "Custom01": 1,
      "CustomParam01": 0,
      "Custom02": 7,
      "CustomParam02": 0,
      "Custom03": 9,
      "CustomParam03": 0
    },
    {
      "$id": 58,
      "Flag": {
        "common": 1
      },
      "KizunaBase": 58,
      "VoiceID": 70,
      "BLC_A": 1,
      "BLC_PARAM_A": 0,
      "BLC_B": 8,
      "BLC_PARAM_B": 0,
      "BLC_C": 0,
      "BLC_D": 0,
      "Custom01": 1,
      "CustomParam01": 0,
      "Custom02": 7,
      "CustomParam02": 0,
      "Custom03": 9,
      "CustomParam03": 0
    },
    {
      "$id": 59,
      "Flag": {
        "common": 1
      },
      "KizunaBase": 59,
      "VoiceID": 71,
      "BLC_A": 1,
      "BLC_PARAM_A": 0,
      "BLC_B": 8,
      "BLC_PARAM_B": 0,
      "BLC_C": 0,
      "BLC_D": 0,
      "Custom01": 1,
      "CustomParam01": 0,
      "Custom02": 7,
      "CustomParam02": 0,
      "Custom03": 9,
      "CustomParam03": 0
    },
    {
      "$id": 60,
      "Flag": {
        "common": 1
      },
      "KizunaBase": 60,
      "VoiceID": 72,
      "BLC_A": 1,
      "BLC_PARAM_A": 0,
      "BLC_B": 8,
      "BLC_PARAM_B": 0,
      "BLC_C": 0,
      "BLC_D": 0,
      "Custom01": 1,
      "CustomParam01": 0,
      "Custom02": 7,
      "CustomParam02": 0,
      "Custom03": 9,
      "CustomParam03": 0
    },
    {
      "$id": 61,
      "Flag": {
        "common": 1
      },
      "KizunaBase": 61,
      "VoiceID": 73,
      "BLC_A": 1,
      "BLC_PARAM_A": 0,
      "BLC_B": 8,
      "BLC_PARAM_B": 0,
      "BLC_C": 0,
      "BLC_D": 0,
      "Custom01": 2,
      "CustomParam01": 0,
      "Custom02": 11,
      "CustomParam02": 2,
      "Custom03": 12,
      "CustomParam03": 2
    },
    {
      "$id": 62,
      "Flag": {
        "common": 1
      },
      "KizunaBase": 62,
      "VoiceID": 74,
      "BLC_A": 1,
      "BLC_PARAM_A": 0,
      "BLC_B": 8,
      "BLC_PARAM_B": 0,
      "BLC_C": 0,
      "BLC_D": 0,
      "Custom01": 2,
      "CustomParam01": 0,
      "Custom02": 11,
      "CustomParam02": 2,
      "Custom03": 12,
      "CustomParam03": 2
    },
    {
      "$id": 63,
      "Flag": {
        "common": 1
      },
      "KizunaBase": 63,
      "VoiceID": 75,
      "BLC_A": 1,
      "BLC_PARAM_A": 0,
      "BLC_B": 8,
      "BLC_PARAM_B": 0,
      "BLC_C": 0,
      "BLC_D": 0,
      "Custom01": 2,
      "CustomParam01": 0,
      "Custom02": 11,
      "CustomParam02": 2,
      "Custom03": 12,
      "CustomParam03": 2
    },
    {
      "$id": 64,
      "Flag": {
        "common": 1
      },
      "KizunaBase": 64,
      "VoiceID": 76,
      "BLC_A": 1,
      "BLC_PARAM_A": 0,
      "BLC_B": 8,
      "BLC_PARAM_B": 0,
      "BLC_C": 0,
      "BLC_D": 0,
      "Custom01": 2,
      "CustomParam01": 0,
      "Custom02": 11,
      "CustomParam02": 2,
      "Custom03": 12,
      "CustomParam03": 2
    },
    {
      "$id": 65,
      "Flag": {
        "common": 1
      },
      "KizunaBase": 65,
      "VoiceID": 77,
      "BLC_A": 1,
      "BLC_PARAM_A": 0,
      "BLC_B": 8,
      "BLC_PARAM_B": 0,
      "BLC_C": 0,
      "BLC_D": 0,
      "Custom01": 2,
      "CustomParam01": 0,
      "Custom02": 11,
      "CustomParam02": 2,
      "Custom03": 12,
      "CustomParam03": 2
    },
    {
      "$id": 66,
      "Flag": {
        "common": 1
      },
      "KizunaBase": 66,
      "VoiceID": 78,
      "BLC_A": 1,
      "BLC_PARAM_A": 0,
      "BLC_B": 8,
      "BLC_PARAM_B": 0,
      "BLC_C": 0,
      "BLC_D": 0,
      "Custom01": 2,
      "CustomParam01": 0,
      "Custom02": 11,
      "CustomParam02": 2,
      "Custom03": 12,
      "CustomParam03": 2
    },
    {
      "$id": 67,
      "Flag": {
        "common": 1
      },
      "KizunaBase": 67,
      "VoiceID": 79,
      "BLC_A": 1,
      "BLC_PARAM_A": 0,
      "BLC_B": 8,
      "BLC_PARAM_B": 0,
      "BLC_C": 0,
      "BLC_D": 0,
      "Custom01": 2,
      "CustomParam01": 0,
      "Custom02": 11,
      "CustomParam02": 2,
      "Custom03": 12,
      "CustomParam03": 2
    },
    {
      "$id": 68,
      "Flag": {
        "common": 1
      },
      "KizunaBase": 68,
      "VoiceID": 80,
      "BLC_A": 1,
      "BLC_PARAM_A": 0,
      "BLC_B": 8,
      "BLC_PARAM_B": 0,
      "BLC_C": 0,
      "BLC_D": 0,
      "Custom01": 2,
      "CustomParam01": 0,
      "Custom02": 11,
      "CustomParam02": 2,
      "Custom03": 12,
      "CustomParam03": 2
    },
    {
      "$id": 69,
      "Flag": {
        "common": 1
      },
      "KizunaBase": 69,
      "VoiceID": 81,
      "BLC_A": 1,
      "BLC_PARAM_A": 0,
      "BLC_B": 8,
      "BLC_PARAM_B": 0,
      "BLC_C": 0,
      "BLC_D": 0,
      "Custom01": 2,
      "CustomParam01": 0,
      "Custom02": 11,
      "CustomParam02": 2,
      "Custom03": 12,
      "CustomParam03": 2
    },
    {
      "$id": 70,
      "Flag": {
        "common": 1
      },
      "KizunaBase": 70,
      "VoiceID": 82,
      "BLC_A": 1,
      "BLC_PARAM_A": 0,
      "BLC_B": 8,
      "BLC_PARAM_B": 0,
      "BLC_C": 0,
      "BLC_D": 0,
      "Custom01": 2,
      "CustomParam01": 0,
      "Custom02": 11,
      "CustomParam02": 2,
      "Custom03": 12,
      "CustomParam03": 2
    },
    {
      "$id": 71,
      "Flag": {
        "common": 1
      },
      "KizunaBase": 71,
      "VoiceID": 83,
      "BLC_A": 1,
      "BLC_PARAM_A": 0,
      "BLC_B": 8,
      "BLC_PARAM_B": 0,
      "BLC_C": 0,
      "BLC_D": 0,
      "Custom01": 2,
      "CustomParam01": 0,
      "Custom02": 11,
      "CustomParam02": 2,
      "Custom03": 12,
      "CustomParam03": 2
    },
    {
      "$id": 72,
      "Flag": {
        "common": 1
      },
      "KizunaBase": 72,
      "VoiceID": 84,
      "BLC_A": 1,
      "BLC_PARAM_A": 0,
      "BLC_B": 8,
      "BLC_PARAM_B": 0,
      "BLC_C": 0,
      "BLC_D": 0,
      "Custom01": 2,
      "CustomParam01": 0,
      "Custom02": 11,
      "CustomParam02": 2,
      "Custom03": 12,
      "CustomParam03": 2
    },
    {
      "$id": 73,
      "Flag": {
        "common": 1
      },
      "KizunaBase": 73,
      "VoiceID": 85,
      "BLC_A": 1,
      "BLC_PARAM_A": 0,
      "BLC_B": 8,
      "BLC_PARAM_B": 0,
      "BLC_C": 0,
      "BLC_D": 0,
      "Custom01": 8,
      "CustomParam01": 4,
      "Custom02": 13,
      "CustomParam02": 0,
      "Custom03": 16,
      "CustomParam03": 0
    },
    {
      "$id": 74,
      "Flag": {
        "common": 1
      },
      "KizunaBase": 74,
      "VoiceID": 86,
      "BLC_A": 1,
      "BLC_PARAM_A": 0,
      "BLC_B": 8,
      "BLC_PARAM_B": 0,
      "BLC_C": 0,
      "BLC_D": 0,
      "Custom01": 8,
      "CustomParam01": 4,
      "Custom02": 13,
      "CustomParam02": 0,
      "Custom03": 16,
      "CustomParam03": 0
    },
    {
      "$id": 75,
      "Flag": {
        "common": 1
      },
      "KizunaBase": 75,
      "VoiceID": 87,
      "BLC_A": 1,
      "BLC_PARAM_A": 0,
      "BLC_B": 8,
      "BLC_PARAM_B": 0,
      "BLC_C": 0,
      "BLC_D": 0,
      "Custom01": 8,
      "CustomParam01": 4,
      "Custom02": 13,
      "CustomParam02": 0,
      "Custom03": 16,
      "CustomParam03": 0
    },
    {
      "$id": 76,
      "Flag": {
        "common": 1
      },
      "KizunaBase": 76,
      "VoiceID": 88,
      "BLC_A": 1,
      "BLC_PARAM_A": 0,
      "BLC_B": 8,
      "BLC_PARAM_B": 0,
      "BLC_C": 0,
      "BLC_D": 0,
      "Custom01": 8,
      "CustomParam01": 4,
      "Custom02": 13,
      "CustomParam02": 0,
      "Custom03": 16,
      "CustomParam03": 0
    },
    {
      "$id": 77,
      "Flag": {
        "common": 1
      },
      "KizunaBase": 77,
      "VoiceID": 89,
      "BLC_A": 1,
      "BLC_PARAM_A": 0,
      "BLC_B": 8,
      "BLC_PARAM_B": 0,
      "BLC_C": 0,
      "BLC_D": 0,
      "Custom01": 3,
      "CustomParam01": 0,
      "Custom02": 4,
      "CustomParam02": 0,
      "Custom03": 15,
      "CustomParam03": 0
    },
    {
      "$id": 78,
      "Flag": {
        "common": 1
      },
      "KizunaBase": 78,
      "VoiceID": 90,
      "BLC_A": 1,
      "BLC_PARAM_A": 0,
      "BLC_B": 8,
      "BLC_PARAM_B": 0,
      "BLC_C": 0,
      "BLC_D": 0,
      "Custom01": 3,
      "CustomParam01": 0,
      "Custom02": 4,
      "CustomParam02": 0,
      "Custom03": 15,
      "CustomParam03": 0
    },
    {
      "$id": 79,
      "Flag": {
        "common": 1
      },
      "KizunaBase": 79,
      "VoiceID": 91,
      "BLC_A": 1,
      "BLC_PARAM_A": 0,
      "BLC_B": 8,
      "BLC_PARAM_B": 0,
      "BLC_C": 0,
      "BLC_D": 0,
      "Custom01": 3,
      "CustomParam01": 0,
      "Custom02": 4,
      "CustomParam02": 0,
      "Custom03": 15,
      "CustomParam03": 0
    },
    {
      "$id": 80,
      "Flag": {
        "common": 1
      },
      "KizunaBase": 80,
      "VoiceID": 92,
      "BLC_A": 1,
      "BLC_PARAM_A": 0,
      "BLC_B": 8,
      "BLC_PARAM_B": 0,
      "BLC_C": 0,
      "BLC_D": 0,
      "Custom01": 3,
      "CustomParam01": 0,
      "Custom02": 4,
      "CustomParam02": 0,
      "Custom03": 15,
      "CustomParam03": 0
    },
    {
      "$id": 81,
      "Flag": {
        "common": 0
      },
      "KizunaBase": 81,
      "VoiceID": 0,
      "BLC_A": 8,
      "BLC_PARAM_A": 0,
      "BLC_B": 5,
      "BLC_PARAM_B": 1039,
      "BLC_C": 1039,
      "BLC_D": 1002,
      "Custom01": 7,
      "CustomParam01": 0,
      "Custom02": 8,
      "CustomParam02": 4,
      "Custom03": 13,
      "CustomParam03": 0
    },
    {
      "$id": 82,
      "Flag": {
        "common": 0
      },
      "KizunaBase": 82,
      "VoiceID": 0,
      "BLC_A": 5,
      "BLC_PARAM_A": 1007,
      "BLC_B": 5,
      "BLC_PARAM_B": 1039,
      "BLC_C": 1001,
      "BLC_D": 1104,
      "Custom01": 1,
      "CustomParam01": 0,
      "Custom02": 11,
      "CustomParam02": 2,
      "Custom03": 16,
      "CustomParam03": 0
    },
    {
      "$id": 83,
      "Flag": {
        "common": 0
      },
      "KizunaBase": 83,
      "VoiceID": 0,
      "BLC_A": 4,
      "BLC_PARAM_A": 1,
      "BLC_B": 7,
      "BLC_PARAM_B": 2,
      "BLC_C": 1107,
      "BLC_D": 1105,
      "Custom01": 4,
      "CustomParam01": 0,
      "Custom02": 9,
      "CustomParam02": 0,
      "Custom03": 15,
      "CustomParam03": 0
    },
    {
      "$id": 84,
      "Flag": {
        "common": 0
      },
      "KizunaBase": 84,
      "VoiceID": 0,
      "BLC_A": 3,
      "BLC_PARAM_A": 5,
      "BLC_B": 4,
      "BLC_PARAM_B": 2,
      "BLC_C": 1106,
      "BLC_D": 1105,
      "Custom01": 3,
      "CustomParam01": 0,
      "Custom02": 7,
      "CustomParam02": 0,
      "Custom03": 10,
      "CustomParam03": 0
    },
    {
      "$id": 85,
      "Flag": {
        "common": 0
      },
      "KizunaBase": 85,
      "VoiceID": 0,
      "BLC_A": 7,
      "BLC_PARAM_A": 2,
      "BLC_B": 8,
      "BLC_PARAM_B": 0,
      "BLC_C": 1109,
      "BLC_D": 1106,
      "Custom01": 5,
      "CustomParam01": 0,
      "Custom02": 6,
      "CustomParam02": 3,
      "Custom03": 13,
      "CustomParam03": 0
    },
    {
      "$id": 86,
      "Flag": {
        "common": 0
      },
      "KizunaBase": 86,
      "VoiceID": 0,
      "BLC_A": 1,
      "BLC_PARAM_A": 0,
      "BLC_B": 5,
      "BLC_PARAM_B": 1001,
      "BLC_C": 1001,
      "BLC_D": 1108,
      "Custom01": 3,
      "CustomParam01": 0,
      "Custom02": 7,
      "CustomParam02": 0,
      "Custom03": 9,
      "CustomParam03": 0
    },
    {
      "$id": 87,
      "Flag": {
        "common": 0
      },
      "KizunaBase": 87,
      "VoiceID": 0,
      "BLC_A": 8,
      "BLC_PARAM_A": 0,
      "BLC_B": 6,
      "BLC_PARAM_B": 30,
      "BLC_C": 1107,
      "BLC_D": 1106,
      "Custom01": 7,
      "CustomParam01": 0,
      "Custom02": 8,
      "CustomParam02": 4,
      "Custom03": 11,
      "CustomParam03": 2
    },
    {
      "$id": 88,
      "Flag": {
        "common": 0
      },
      "KizunaBase": 88,
      "VoiceID": 0,
      "BLC_A": 7,
      "BLC_PARAM_A": 1,
      "BLC_B": 6,
      "BLC_PARAM_B": 30,
      "BLC_C": 0,
      "BLC_D": 0,
      "Custom01": 3,
      "CustomParam01": 0,
      "Custom02": 7,
      "CustomParam02": 0,
      "Custom03": 15,
      "CustomParam03": 0
    },
    {
      "$id": 89,
      "Flag": {
        "common": 0
      },
      "KizunaBase": 89,
      "VoiceID": 0,
      "BLC_A": 8,
      "BLC_PARAM_A": 0,
      "BLC_B": 1,
      "BLC_PARAM_B": 0,
      "BLC_C": 0,
      "BLC_D": 0,
      "Custom01": 10,
      "CustomParam01": 0,
      "Custom02": 7,
      "CustomParam02": 0,
      "Custom03": 8,
      "CustomParam03": 4
    },
    {
      "$id": 90,
      "Flag": {
        "common": 0
      },
      "KizunaBase": 90,
      "VoiceID": 0,
      "BLC_A": 7,
      "BLC_PARAM_A": 1,
      "BLC_B": 3,
      "BLC_PARAM_B": 5,
      "BLC_C": 0,
      "BLC_D": 0,
      "Custom01": 1,
      "CustomParam01": 0,
      "Custom02": 5,
      "CustomParam02": 0,
      "Custom03": 6,
      "CustomParam03": 3
    },
    {
      "$id": 91,
      "Flag": {
        "common": 0
      },
      "KizunaBase": 91,
      "VoiceID": 0,
      "BLC_A": 8,
      "BLC_PARAM_A": 0,
      "BLC_B": 7,
      "BLC_PARAM_B": 1,
      "BLC_C": 0,
      "BLC_D": 0,
      "Custom01": 4,
      "CustomParam01": 0,
      "Custom02": 8,
      "CustomParam02": 4,
      "Custom03": 12,
      "CustomParam03": 2
    },
    {
      "$id": 92,
      "Flag": {
        "common": 0
      },
      "KizunaBase": 92,
      "VoiceID": 0,
      "BLC_A": 6,
      "BLC_PARAM_A": 30,
      "BLC_B": 3,
      "BLC_PARAM_B": 6,
      "BLC_C": 0,
      "BLC_D": 0,
      "Custom01": 1,
      "CustomParam01": 0,
      "Custom02": 11,
      "CustomParam02": 3,
      "Custom03": 6,
      "CustomParam03": 3
    },
    {
      "$id": 93,
      "Flag": {
        "common": 0
      },
      "KizunaBase": 93,
      "VoiceID": 0,
      "BLC_A": 8,
      "BLC_PARAM_A": 0,
      "BLC_B": 4,
      "BLC_PARAM_B": 20,
      "BLC_C": 0,
      "BLC_D": 0,
      "Custom01": 9,
      "CustomParam01": 0,
      "Custom02": 4,
      "CustomParam02": 0,
      "Custom03": 8,
      "CustomParam03": 4
    },
    {
      "$id": 94,
      "Flag": {
        "common": 0
      },
      "KizunaBase": 94,
      "VoiceID": 0,
      "BLC_A": 1,
      "BLC_PARAM_A": 0,
      "BLC_B": 2,
      "BLC_PARAM_B": 0,
      "BLC_C": 0,
      "BLC_D": 0,
      "Custom01": 4,
      "CustomParam01": 0,
      "Custom02": 7,
      "CustomParam02": 0,
      "Custom03": 11,
      "CustomParam03": 3
    },
    {
      "$id": 95,
      "Flag": {
        "common": 0
      },
      "KizunaBase": 95,
      "VoiceID": 0,
      "BLC_A": 1,
      "BLC_PARAM_A": 0,
      "BLC_B": 4,
      "BLC_PARAM_B": 22,
      "BLC_C": 0,
      "BLC_D": 0,
      "Custom01": 9,
      "CustomParam01": 0,
      "Custom02": 7,
      "CustomParam02": 0,
      "Custom03": 5,
      "CustomParam03": 0
    },
    {
      "$id": 96,
      "Flag": {
        "common": 0
      },
      "KizunaBase": 96,
      "VoiceID": 0,
      "BLC_A": 6,
      "BLC_PARAM_A": 30,
      "BLC_B": 8,
      "BLC_PARAM_B": 0,
      "BLC_C": 0,
      "BLC_D": 0,
      "Custom01": 5,
      "CustomParam01": 0,
      "Custom02": 3,
      "CustomParam02": 0,
      "Custom03": 12,
      "CustomParam03": 2
    }
  ]
}