{
  "schema": [
    {
      "name": "evtName",
      "type": 7
    },
    {
      "name": "mstxt",
      "type": 7
    },
    {
      "name": "setupID",
      "type": 2
    },
    {
      "name": "chgStID",
      "type": 2
    },
    {
      "name": "chgEdID",
      "type": 2
    },
    {
      "name": "category",
      "type": 1
    },
    {
      "name": "weather",
      "type": 1
    },
    {
      "name": "clock",
      "type": 7
    },
    {
      "name": "clockStop",
      "type": 1
    },
    {
      "name": "cloud",
      "type": 1
    },
    {
      "name": "text",
      "type": 1
    },
    {
      "name": "opFadeOutEnable",
      "type": 1
    },
    {
      "name": "opFadeOut",
      "type": 2
    },
    {
      "name": "opFadeWait",
      "type": 2
    },
    {
      "name": "opFadeInEnable",
      "type": 1
    },
    {
      "name": "opFadeIn",
      "type": 2
    },
    {
      "name": "opFadeColR",
      "type": 1
    },
    {
      "name": "opFadeColG",
      "type": 1
    },
    {
      "name": "opFadeColB",
      "type": 1
    },
    {
      "name": "edFadeOutEnable",
      "type": 1
    },
    {
      "name": "edFadeOut",
      "type": 2
    },
    {
      "name": "edFadeWait",
      "type": 2
    },
    {
      "name": "edFadeInEnable",
      "type": 1
    },
    {
      "name": "edFadeIn",
      "type": 2
    },
    {
      "name": "edFadeColR",
      "type": 1
    },
    {
      "name": "edFadeColG",
      "type": 1
    },
    {
      "name": "edFadeColB",
      "type": 1
    },
    {
      "name": "stFormID",
      "type": 2
    },
    {
      "name": "edFormID",
      "type": 2
    },
    {
      "name": "opBgm",
      "type": 1
    },
    {
      "name": "edBgm",
      "type": 1
    },
    {
      "name": "hideNpc",
      "type": 1
    },
    {
      "name": "hideEne",
      "type": 1
    },
    {
      "name": "hideMob",
      "type": 1
    },
    {
      "name": "hideMap",
      "type": 1
    },
    {
      "name": "outsiderOpt",
      "type": 2
    },
    {
      "name": "outsiderEnable",
      "type": 1
    },
    {
      "name": "outsiderType",
      "type": 1
    },
    {
      "name": "outsiderX",
      "type": 8
    },
    {
      "name": "outsiderY",
      "type": 8
    },
    {
      "name": "outsiderZ",
      "type": 8
    },
    {
      "name": "outsiderR",
      "type": 8
    },
    {
      "name": "listenType",
      "type": 1
    },
    {
      "name": "listenX",
      "type": 8
    },
    {
      "name": "listenY",
      "type": 8
    },
    {
      "name": "listenZ",
      "type": 8
    },
    {
      "name": "nextID",
      "type": 2
    },
    {
      "name": "zoneID",
      "type": 2
    },
    {
      "name": "zoneX",
      "type": 8
    },
    {
      "name": "zoneY",
      "type": 8
    },
    {
      "name": "zoneZ",
      "type": 8
    },
    {
      "name": "zoneR",
      "type": 8
    },
    {
      "name": "chapID",
      "type": 1
    },
    {
      "name": "linkID",
      "type": 2
    },
    {
      "name": "jijiDisp",
      "type": 1
    },
    {
      "name": "wpnDisp",
      "type": 2
    },
    {
      "name": "colFilterNear",
      "type": 2
    },
    {
      "name": "colFilterFar",
      "type": 2
    },
    {
      "name": "envSeam",
      "type": 2
    },
    {
      "name": "evtLight",
      "type": 7
    },
    {
      "name": "hood",
      "type": 1
    },
    {
      "name": "voice",
      "type": 1
    },
    {
      "name": "cssnd",
      "type": 1
    },
    {
      "name": "scriptName",
      "type": 7
    },
    {
      "name": "scriptStartId",
      "type": 6
    },
    {
      "name": "toneMap",
      "type": 8
    },
    {
      "name": "noRetarget",
      "type": 1
    }
  ],
  "rows": [
    {
      "$id": 19001,
      "evtName": "bf80000101",
      "mstxt": "",
      "setupID": 0,
      "chgStID": 0,
      "chgEdID": 0,
      "category": 4,
      "weather": 0,
      "clock": "",
      "clockStop": 0,
      "cloud": 0,
      "text": 1,
      "opFadeOutEnable": 1,
      "opFadeOut": 10,
      "opFadeWait": 0,
      "opFadeInEnable": 1,
      "opFadeIn": 15,
      "opFadeColR": 1,
      "opFadeColG": 1,
      "opFadeColB": 1,
      "edFadeOutEnable": 0,
      "edFadeOut": 0,
      "edFadeWait": 0,
      "edFadeInEnable": 0,
      "edFadeIn": 0,
      "edFadeColR": 0,
      "edFadeColG": 0,
      "edFadeColB": 0,
      "stFormID": 0,
      "edFormID": 0,
      "opBgm": 0,
      "edBgm": 0,
      "hideNpc": 0,
      "hideEne": 0,
      "hideMob": 0,
      "hideMap": 1,
      "outsiderOpt": 0,
      "outsiderEnable": 0,
      "outsiderType": 1,
      "outsiderX": 0.0,
      "outsiderY": 0.0,
      "outsiderZ": 0.0,
      "outsiderR": 0.0,
      "listenType": 0,
      "listenX": 0.0,
      "listenY": 0.0,
      "listenZ": 0.0,
      "nextID": 0,
      "zoneID": 46,
      "zoneX": 0.0,
      "zoneY": 0.0,
      "zoneZ": 0.0,
      "zoneR": 0.0,
      "chapID": 1,
      "linkID": 0,
      "jijiDisp": 0,
      "wpnDisp": 1,
      "colFilterNear": 0,
      "colFilterFar": 0,
      "envSeam": 0,
      "evtLight": "",
      "hood": 1,
      "voice": 1,
      "cssnd": 1,
      "scriptName": "",
      "scriptStartId": 0,
      "toneMap": 0.0,
      "noRetarget": 0
    },
    {
      "$id": 19002,
      "evtName": "bf80001101",
      "mstxt": "blade/bf80001101",
      "setupID": 0,
      "chgStID": 0,
      "chgEdID": 0,
      "category": 4,
      "weather": 0,
      "clock": "",
      "clockStop": 0,
      "cloud": 0,
      "text": 1,
      "opFadeOutEnable": 1,
      "opFadeOut": 10,
      "opFadeWait": 0,
      "opFadeInEnable": 1,
      "opFadeIn": 15,
      "opFadeColR": 1,
      "opFadeColG": 1,
      "opFadeColB": 1,
      "edFadeOutEnable": 0,
      "edFadeOut": 0,
      "edFadeWait": 0,
      "edFadeInEnable": 0,
      "edFadeIn": 0,
      "edFadeColR": 0,
      "edFadeColG": 0,
      "edFadeColB": 0,
      "stFormID": 0,
      "edFormID": 0,
      "opBgm": 0,
      "edBgm": 0,
      "hideNpc": 0,
      "hideEne": 0,
      "hideMob": 0,
      "hideMap": 1,
      "outsiderOpt": 0,
      "outsiderEnable": 0,
      "outsiderType": 1,
      "outsiderX": 0.0,
      "outsiderY": 0.0,
      "outsiderZ": 0.0,
      "outsiderR": 0.0,
      "listenType": 0,
      "listenX": 0.0,
      "listenY": 0.0,
      "listenZ": 0.0,
      "nextID": 0,
      "zoneID": 46,
      "zoneX": 0.0,
      "zoneY": 0.0,
      "zoneZ": 0.0,
      "zoneR": 0.0,
      "chapID": 1,
      "linkID": 0,
      "jijiDisp": 0,
      "wpnDisp": 1,
      "colFilterNear": 0,
      "colFilterFar": 0,
      "envSeam": 0,
      "evtLight": "",
      "hood": 1,
      "voice": 1,
      "cssnd": 1,
      "scriptName": "",
      "scriptStartId": 0,
      "toneMap": 0.0,
      "noRetarget": 0
    },
    {
      "$id": 19003,
      "evtName": "bf80001201",
      "mstxt": "blade/bf80001201",
      "setupID": 0,
      "chgStID": 0,
      "chgEdID": 0,
      "category": 4,
      "weather": 0,
      "clock": "",
      "clockStop": 0,
      "cloud": 0,
      "text": 1,
      "opFadeOutEnable": 1,
      "opFadeOut": 10,
      "opFadeWait": 0,
      "opFadeInEnable": 1,
      "opFadeIn": 15,
      "opFadeColR": 1,
      "opFadeColG": 1,
      "opFadeColB": 1,
      "edFadeOutEnable": 0,
      "edFadeOut": 0,
      "edFadeWait": 0,
      "edFadeInEnable": 0,
      "edFadeIn": 0,
      "edFadeColR": 0,
      "edFadeColG": 0,
      "edFadeColB": 0,
      "stFormID": 0,
      "edFormID": 0,
      "opBgm": 0,
      "edBgm": 0,
      "hideNpc": 0,
      "hideEne": 0,
      "hideMob": 0,
      "hideMap": 1,
      "outsiderOpt": 0,
      "outsiderEnable": 0,
      "outsiderType": 1,
      "outsiderX": 0.0,
      "outsiderY": 0.0,
      "outsiderZ": 0.0,
      "outsiderR": 0.0,
      "listenType": 0,
      "listenX": 0.0,
      "listenY": 0.0,
      "listenZ": 0.0,
      "nextID": 0,
      "zoneID": 46,
      "zoneX": 0.0,
      "zoneY": 0.0,
      "zoneZ": 0.0,
      "zoneR": 0.0,
      "chapID": 1,
      "linkID": 0,
      "jijiDisp": 0,
      "wpnDisp": 1,
      "colFilterNear": 0,
      "colFilterFar": 0,
      "envSeam": 0,
      "evtLight": "",
      "hood": 1,
      "voice": 1,
      "cssnd": 1,
      "scriptName": "",
      "scriptStartId": 0,
      "toneMap": 0.0,
      "noRetarget": 0
    },
    {
      "$id": 19004,
      "evtName": "bf80302801",
      "mstxt": "blade/bf80302801",
      "setupID": 0,
      "chgStID": 0,
      "chgEdID": 0,
      "category": 4,
      "weather": 0,
      "clock": "",
      "clockStop": 0,
      "cloud": 0,
      "text": 1,
      "opFadeOutEnable": 1,
      "opFadeOut": 10,
      "opFadeWait": 0,
      "opFadeInEnable": 1,
      "opFadeIn": 15,
      "opFadeColR": 1,
      "opFadeColG": 1,
      "opFadeColB": 1,
      "edFadeOutEnable": 0,
      "edFadeOut": 0,
      "edFadeWait": 0,
      "edFadeInEnable": 0,
      "edFadeIn": 0,
      "edFadeColR": 0,
      "edFadeColG": 0,
      "edFadeColB": 0,
      "stFormID": 0,
      "edFormID": 0,
      "opBgm": 0,
      "edBgm": 0,
      "hideNpc": 0,
      "hideEne": 0,
      "hideMob": 0,
      "hideMap": 1,
      "outsiderOpt": 0,
      "outsiderEnable": 0,
      "outsiderType": 1,
      "outsiderX": 0.0,
      "outsiderY": 0.0,
      "outsiderZ": 0.0,
      "outsiderR": 0.0,
      "listenType": 0,
      "listenX": 0.0,
      "listenY": 0.0,
      "listenZ": 0.0,
      "nextID": 0,
      "zoneID": 46,
      "zoneX": 0.0,
      "zoneY": 0.0,
      "zoneZ": 0.0,
      "zoneR": 0.0,
      "chapID": 1,
      "linkID": 0,
      "jijiDisp": 0,
      "wpnDisp": 1,
      "colFilterNear": 0,
      "colFilterFar": 0,
      "envSeam": 0,
      "evtLight": "",
      "hood": 1,
      "voice": 1,
      "cssnd": 1,
      "scriptName": "",
      "scriptStartId": 0,
      "toneMap": 0.0,
      "noRetarget": 0
    },
    {
      "$id": 19005,
      "evtName": "bf80302901",
      "mstxt": "blade/bf80302901",
      "setupID": 0,
      "chgStID": 0,
      "chgEdID": 0,
      "category": 4,
      "weather": 0,
      "clock": "",
      "clockStop": 0,
      "cloud": 0,
      "text": 1,
      "opFadeOutEnable": 1,
      "opFadeOut": 10,
      "opFadeWait": 0,
      "opFadeInEnable": 1,
      "opFadeIn": 15,
      "opFadeColR": 1,
      "opFadeColG": 1,
      "opFadeColB": 1,
      "edFadeOutEnable": 0,
      "edFadeOut": 0,
      "edFadeWait": 0,
      "edFadeInEnable": 0,
      "edFadeIn": 0,
      "edFadeColR": 0,
      "edFadeColG": 0,
      "edFadeColB": 0,
      "stFormID": 0,
      "edFormID": 0,
      "opBgm": 0,
      "edBgm": 0,
      "hideNpc": 0,
      "hideEne": 0,
      "hideMob": 0,
      "hideMap": 1,
      "outsiderOpt": 0,
      "outsiderEnable": 0,
      "outsiderType": 1,
      "outsiderX": 0.0,
      "outsiderY": 0.0,
      "outsiderZ": 0.0,
      "outsiderR": 0.0,
      "listenType": 0,
      "listenX": 0.0,
      "listenY": 0.0,
      "listenZ": 0.0,
      "nextID": 0,
      "zoneID": 46,
      "zoneX": 0.0,
      "zoneY": 0.0,
      "zoneZ": 0.0,
      "zoneR": 0.0,
      "chapID": 1,
      "linkID": 0,
      "jijiDisp": 0,
      "wpnDisp": 1,
      "colFilterNear": 0,
      "colFilterFar": 0,
      "envSeam": 0,
      "evtLight": "",
      "hood": 1,
      "voice": 1,
      "cssnd": 1,
      "scriptName": "",
      "scriptStartId": 0,
      "toneMap": 0.0,
      "noRetarget": 0
    },
    {
      "$id": 19006,
      "evtName": "bf80001301",
      "mstxt": "blade/bf80001301",
      "setupID": 0,
      "chgStID": 0,
      "chgEdID": 0,
      "category": 4,
      "weather": 0,
      "clock": "",
      "clockStop": 0,
      "cloud": 0,
      "text": 1,
      "opFadeOutEnable": 1,
      "opFadeOut": 10,
      "opFadeWait": 0,
      "opFadeInEnable": 1,
      "opFadeIn": 15,
      "opFadeColR": 1,
      "opFadeColG": 1,
      "opFadeColB": 1,
      "edFadeOutEnable": 0,
      "edFadeOut": 0,
      "edFadeWait": 0,
      "edFadeInEnable": 0,
      "edFadeIn": 0,
      "edFadeColR": 0,
      "edFadeColG": 0,
      "edFadeColB": 0,
      "stFormID": 0,
      "edFormID": 0,
      "opBgm": 0,
      "edBgm": 0,
      "hideNpc": 0,
      "hideEne": 0,
      "hideMob": 0,
      "hideMap": 1,
      "outsiderOpt": 0,
      "outsiderEnable": 0,
      "outsiderType": 1,
      "outsiderX": 0.0,
      "outsiderY": 0.0,
      "outsiderZ": 0.0,
      "outsiderR": 0.0,
      "listenType": 0,
      "listenX": 0.0,
      "listenY": 0.0,
      "listenZ": 0.0,
      "nextID": 0,
      "zoneID": 46,
      "zoneX": 0.0,
      "zoneY": 0.0,
      "zoneZ": 0.0,
      "zoneR": 0.0,
      "chapID": 1,
      "linkID": 0,
      "jijiDisp": 0,
      "wpnDisp": 1,
      "colFilterNear": 0,
      "colFilterFar": 0,
      "envSeam": 0,
      "evtLight": "",
      "hood": 1,
      "voice": 1,
      "cssnd": 1,
      "scriptName": "",
      "scriptStartId": 0,
      "toneMap": 0.0,
      "noRetarget": 0
    },
    {
      "$id": 19007,
      "evtName": "bf80001401",
      "mstxt": "blade/bf80001401",
      "setupID": 0,
      "chgStID": 0,
      "chgEdID": 0,
      "category": 4,
      "weather": 0,
      "clock": "",
      "clockStop": 0,
      "cloud": 0,
      "text": 1,
      "opFadeOutEnable": 1,
      "opFadeOut": 10,
      "opFadeWait": 0,
      "opFadeInEnable": 1,
      "opFadeIn": 15,
      "opFadeColR": 1,
      "opFadeColG": 1,
      "opFadeColB": 1,
      "edFadeOutEnable": 0,
      "edFadeOut": 0,
      "edFadeWait": 0,
      "edFadeInEnable": 0,
      "edFadeIn": 0,
      "edFadeColR": 0,
      "edFadeColG": 0,
      "edFadeColB": 0,
      "stFormID": 0,
      "edFormID": 0,
      "opBgm": 0,
      "edBgm": 0,
      "hideNpc": 0,
      "hideEne": 0,
      "hideMob": 0,
      "hideMap": 1,
      "outsiderOpt": 0,
      "outsiderEnable": 0,
      "outsiderType": 1,
      "outsiderX": 0.0,
      "outsiderY": 0.0,
      "outsiderZ": 0.0,
      "outsiderR": 0.0,
      "listenType": 0,
      "listenX": 0.0,
      "listenY": 0.0,
      "listenZ": 0.0,
      "nextID": 0,
      "zoneID": 46,
      "zoneX": 0.0,
      "zoneY": 0.0,
      "zoneZ": 0.0,
      "zoneR": 0.0,
      "chapID": 1,
      "linkID": 0,
      "jijiDisp": 0,
      "wpnDisp": 1,
      "colFilterNear": 0,
      "colFilterFar": 0,
      "envSeam": 0,
      "evtLight": "",
      "hood": 1,
      "voice": 1,
      "cssnd": 1,
      "scriptName": "",
      "scriptStartId": 0,
      "toneMap": 0.0,
      "noRetarget": 0
    },
    {
      "$id": 19008,
      "evtName": "bf80001501",
      "mstxt": "blade/bf80001501",
      "setupID": 0,
      "chgStID": 0,
      "chgEdID": 0,
      "category": 4,
      "weather": 0,
      "clock": "",
      "clockStop": 0,
      "cloud": 0,
      "text": 1,
      "opFadeOutEnable": 1,
      "opFadeOut": 10,
      "opFadeWait": 0,
      "opFadeInEnable": 1,
      "opFadeIn": 15,
      "opFadeColR": 1,
      "opFadeColG": 1,
      "opFadeColB": 1,
      "edFadeOutEnable": 0,
      "edFadeOut": 0,
      "edFadeWait": 0,
      "edFadeInEnable": 0,
      "edFadeIn": 0,
      "edFadeColR": 0,
      "edFadeColG": 0,
      "edFadeColB": 0,
      "stFormID": 0,
      "edFormID": 0,
      "opBgm": 0,
      "edBgm": 0,
      "hideNpc": 0,
      "hideEne": 0,
      "hideMob": 0,
      "hideMap": 1,
      "outsiderOpt": 0,
      "outsiderEnable": 0,
      "outsiderType": 1,
      "outsiderX": 0.0,
      "outsiderY": 0.0,
      "outsiderZ": 0.0,
      "outsiderR": 0.0,
      "listenType": 0,
      "listenX": 0.0,
      "listenY": 0.0,
      "listenZ": 0.0,
      "nextID": 0,
      "zoneID": 46,
      "zoneX": 0.0,
      "zoneY": 0.0,
      "zoneZ": 0.0,
      "zoneR": 0.0,
      "chapID": 1,
      "linkID": 0,
      "jijiDisp": 0,
      "wpnDisp": 1,
      "colFilterNear": 0,
      "colFilterFar": 0,
      "envSeam": 0,
      "evtLight": "",
      "hood": 1,
      "voice": 1,
      "cssnd": 1,
      "scriptName": "",
      "scriptStartId": 0,
      "toneMap": 0.0,
      "noRetarget": 0
    },
    {
      "$id": 19009,
      "evtName": "bf80001601",
      "mstxt": "blade/bf80001601",
      "setupID": 0,
      "chgStID": 0,
      "chgEdID": 0,
      "category": 4,
      "weather": 0,
      "clock": "",
      "clockStop": 0,
      "cloud": 0,
      "text": 1,
      "opFadeOutEnable": 1,
      "opFadeOut": 10,
      "opFadeWait": 0,
      "opFadeInEnable": 1,
      "opFadeIn": 15,
      "opFadeColR": 1,
      "opFadeColG": 1,
      "opFadeColB": 1,
      "edFadeOutEnable": 0,
      "edFadeOut": 0,
      "edFadeWait": 0,
      "edFadeInEnable": 0,
      "edFadeIn": 0,
      "edFadeColR": 0,
      "edFadeColG": 0,
      "edFadeColB": 0,
      "stFormID": 0,
      "edFormID": 0,
      "opBgm": 0,
      "edBgm": 0,
      "hideNpc": 0,
      "hideEne": 0,
      "hideMob": 0,
      "hideMap": 1,
      "outsiderOpt": 0,
      "outsiderEnable": 0,
      "outsiderType": 1,
      "outsiderX": 0.0,
      "outsiderY": 0.0,
      "outsiderZ": 0.0,
      "outsiderR": 0.0,
      "listenType": 0,
      "listenX": 0.0,
      "listenY": 0.0,
      "listenZ": 0.0,
      "nextID": 0,
      "zoneID": 46,
      "zoneX": 0.0,
      "zoneY": 0.0,
      "zoneZ": 0.0,
      "zoneR": 0.0,
      "chapID": 1,
      "linkID": 0,
      "jijiDisp": 0,
      "wpnDisp": 1,
      "colFilterNear": 0,
      "colFilterFar": 0,
      "envSeam": 0,
      "evtLight": "",
      "hood": 1,
      "voice": 1,
      "cssnd": 1,
      "scriptName": "",
      "scriptStartId": 0,
      "toneMap": 0.0,
      "noRetarget": 0
    },
    {
      "$id": 19010,
      "evtName": "bf80200101",
      "mstxt": "blade/bf80200100",
      "setupID": 0,
      "chgStID": 0,
      "chgEdID": 0,
      "category": 4,
      "weather": 0,
      "clock": "",
      "clockStop": 0,
      "cloud": 0,
      "text": 1,
      "opFadeOutEnable": 1,
      "opFadeOut": 10,
      "opFadeWait": 0,
      "opFadeInEnable": 1,
      "opFadeIn": 15,
      "opFadeColR": 1,
      "opFadeColG": 1,
      "opFadeColB": 1,
      "edFadeOutEnable": 0,
      "edFadeOut": 0,
      "edFadeWait": 0,
      "edFadeInEnable": 0,
      "edFadeIn": 0,
      "edFadeColR": 0,
      "edFadeColG": 0,
      "edFadeColB": 0,
      "stFormID": 0,
      "edFormID": 0,
      "opBgm": 0,
      "edBgm": 0,
      "hideNpc": 0,
      "hideEne": 0,
      "hideMob": 0,
      "hideMap": 1,
      "outsiderOpt": 0,
      "outsiderEnable": 0,
      "outsiderType": 1,
      "outsiderX": 0.0,
      "outsiderY": 0.0,
      "outsiderZ": 0.0,
      "outsiderR": 0.0,
      "listenType": 0,
      "listenX": 0.0,
      "listenY": 0.0,
      "listenZ": 0.0,
      "nextID": 0,
      "zoneID": 46,
      "zoneX": 0.0,
      "zoneY": 0.0,
      "zoneZ": 0.0,
      "zoneR": 0.0,
      "chapID": 1,
      "linkID": 0,
      "jijiDisp": 0,
      "wpnDisp": 1,
      "colFilterNear": 0,
      "colFilterFar": 0,
      "envSeam": 0,
      "evtLight": "",
      "hood": 1,
      "voice": 1,
      "cssnd": 1,
      "scriptName": "",
      "scriptStartId": 0,
      "toneMap": 0.0,
      "noRetarget": 0
    },
    {
      "$id": 19011,
      "evtName": "bf80200102",
      "mstxt": "blade/bf80200100",
      "setupID": 0,
      "chgStID": 0,
      "chgEdID": 0,
      "category": 4,
      "weather": 0,
      "clock": "",
      "clockStop": 0,
      "cloud": 0,
      "text": 1,
      "opFadeOutEnable": 1,
      "opFadeOut": 10,
      "opFadeWait": 0,
      "opFadeInEnable": 1,
      "opFadeIn": 15,
      "opFadeColR": 1,
      "opFadeColG": 1,
      "opFadeColB": 1,
      "edFadeOutEnable": 0,
      "edFadeOut": 0,
      "edFadeWait": 0,
      "edFadeInEnable": 0,
      "edFadeIn": 0,
      "edFadeColR": 0,
      "edFadeColG": 0,
      "edFadeColB": 0,
      "stFormID": 0,
      "edFormID": 0,
      "opBgm": 0,
      "edBgm": 0,
      "hideNpc": 0,
      "hideEne": 0,
      "hideMob": 0,
      "hideMap": 1,
      "outsiderOpt": 0,
      "outsiderEnable": 0,
      "outsiderType": 1,
      "outsiderX": 0.0,
      "outsiderY": 0.0,
      "outsiderZ": 0.0,
      "outsiderR": 0.0,
      "listenType": 0,
      "listenX": 0.0,
      "listenY": 0.0,
      "listenZ": 0.0,
      "nextID": 0,
      "zoneID": 46,
      "zoneX": 0.0,
      "zoneY": 0.0,
      "zoneZ": 0.0,
      "zoneR": 0.0,
      "chapID": 1,
      "linkID": 0,
      "jijiDisp": 0,
      "wpnDisp": 1,
      "colFilterNear": 0,
      "colFilterFar": 0,
      "envSeam": 0,
      "evtLight": "",
      "hood": 1,
      "voice": 1,
      "cssnd": 1,
      "scriptName": "",
      "scriptStartId": 0,
      "toneMap": 0.0,
      "noRetarget": 0
    },
    {
      "$id": 19012,
      "evtName": "bf80200103",
      "mstxt": "blade/bf80200100",
      "setupID": 0,
      "chgStID": 0,
      "chgEdID": 0,
      "category": 4,
      "weather": 0,
      "clock": "",
      "clockStop": 0,
      "cloud": 0,
      "text": 1,
      "opFadeOutEnable": 1,
      "opFadeOut": 10,
      "opFadeWait": 0,
      "opFadeInEnable": 1,
      "opFadeIn": 15,
      "opFadeColR": 1,
      "opFadeColG": 1,
      "opFadeColB": 1,
      "edFadeOutEnable": 0,
      "edFadeOut": 0,
      "edFadeWait": 0,
      "edFadeInEnable": 0,
      "edFadeIn": 0,
      "edFadeColR": 0,
      "edFadeColG": 0,
      "edFadeColB": 0,
      "stFormID": 0,
      "edFormID": 0,
      "opBgm": 0,
      "edBgm": 0,
      "hideNpc": 0,
      "hideEne": 0,
      "hideMob": 0,
      "hideMap": 1,
      "outsiderOpt": 0,
      "outsiderEnable": 0,
      "outsiderType": 1,
      "outsiderX": 0.0,
      "outsiderY": 0.0,
      "outsiderZ": 0.0,
      "outsiderR": 0.0,
      "listenType": 0,
      "listenX": 0.0,
      "listenY": 0.0,
      "listenZ": 0.0,
      "nextID": 0,
      "zoneID": 46,
      "zoneX": 0.0,
      "zoneY": 0.0,
      "zoneZ": 0.0,
      "zoneR": 0.0,
      "chapID": 1,
      "linkID": 0,
      "jijiDisp": 0,
      "wpnDisp": 1,
      "colFilterNear": 0,
      "colFilterFar": 0,
      "envSeam": 0,
      "evtLight": "",
      "hood": 1,
      "voice": 1,
      "cssnd": 1,
      "scriptName": "",
      "scriptStartId": 0,
      "toneMap": 0.0,
      "noRetarget": 0
    },
    {
      "$id": 19013,
      "evtName": "bf80200104",
      "mstxt": "blade/bf80200100",
      "setupID": 0,
      "chgStID": 0,
      "chgEdID": 0,
      "category": 4,
      "weather": 0,
      "clock": "",
      "clockStop": 0,
      "cloud": 0,
      "text": 1,
      "opFadeOutEnable": 1,
      "opFadeOut": 10,
      "opFadeWait": 0,
      "opFadeInEnable": 1,
      "opFadeIn": 15,
      "opFadeColR": 1,
      "opFadeColG": 1,
      "opFadeColB": 1,
      "edFadeOutEnable": 0,
      "edFadeOut": 0,
      "edFadeWait": 0,
      "edFadeInEnable": 0,
      "edFadeIn": 0,
      "edFadeColR": 0,
      "edFadeColG": 0,
      "edFadeColB": 0,
      "stFormID": 0,
      "edFormID": 0,
      "opBgm": 0,
      "edBgm": 0,
      "hideNpc": 0,
      "hideEne": 0,
      "hideMob": 0,
      "hideMap": 1,
      "outsiderOpt": 0,
      "outsiderEnable": 0,
      "outsiderType": 1,
      "outsiderX": 0.0,
      "outsiderY": 0.0,
      "outsiderZ": 0.0,
      "outsiderR": 0.0,
      "listenType": 0,
      "listenX": 0.0,
      "listenY": 0.0,
      "listenZ": 0.0,
      "nextID": 0,
      "zoneID": 46,
      "zoneX": 0.0,
      "zoneY": 0.0,
      "zoneZ": 0.0,
      "zoneR": 0.0,
      "chapID": 1,
      "linkID": 0,
      "jijiDisp": 0,
      "wpnDisp": 1,
      "colFilterNear": 0,
      "colFilterFar": 0,
      "envSeam": 0,
      "evtLight": "",
      "hood": 1,
      "voice": 1,
      "cssnd": 1,
      "scriptName": "",
      "scriptStartId": 0,
      "toneMap": 0.0,
      "noRetarget": 0
    },
    {
      "$id": 19014,
      "evtName": "bf80200105",
      "mstxt": "blade/bf80200100",
      "setupID": 0,
      "chgStID": 0,
      "chgEdID": 0,
      "category": 4,
      "weather": 0,
      "clock": "",
      "clockStop": 0,
      "cloud": 0,
      "text": 1,
      "opFadeOutEnable": 1,
      "opFadeOut": 10,
      "opFadeWait": 0,
      "opFadeInEnable": 1,
      "opFadeIn": 15,
      "opFadeColR": 1,
      "opFadeColG": 1,
      "opFadeColB": 1,
      "edFadeOutEnable": 0,
      "edFadeOut": 0,
      "edFadeWait": 0,
      "edFadeInEnable": 0,
      "edFadeIn": 0,
      "edFadeColR": 0,
      "edFadeColG": 0,
      "edFadeColB": 0,
      "stFormID": 0,
      "edFormID": 0,
      "opBgm": 0,
      "edBgm": 0,
      "hideNpc": 0,
      "hideEne": 0,
      "hideMob": 0,
      "hideMap": 1,
      "outsiderOpt": 0,
      "outsiderEnable": 0,
      "outsiderType": 1,
      "outsiderX": 0.0,
      "outsiderY": 0.0,
      "outsiderZ": 0.0,
      "outsiderR": 0.0,
      "listenType": 0,
      "listenX": 0.0,
      "listenY": 0.0,
      "listenZ": 0.0,
      "nextID": 0,
      "zoneID": 46,
      "zoneX": 0.0,
      "zoneY": 0.0,
      "zoneZ": 0.0,
      "zoneR": 0.0,
      "chapID": 1,
      "linkID": 0,
      "jijiDisp": 0,
      "wpnDisp": 1,
      "colFilterNear": 0,
      "colFilterFar": 0,
      "envSeam": 0,
      "evtLight": "",
      "hood": 1,
      "voice": 1,
      "cssnd": 1,
      "scriptName": "",
      "scriptStartId": 0,
      "toneMap": 0.0,
      "noRetarget": 0
    },
    {
      "$id": 19015,
      "evtName": "bf80200106",
      "mstxt": "blade/bf80200100",
      "setupID": 0,
      "chgStID": 0,
      "chgEdID": 0,
      "category": 4,
      "weather": 0,
      "clock": "",
      "clockStop": 0,
      "cloud": 0,
      "text": 1,
      "opFadeOutEnable": 1,
      "opFadeOut": 10,
      "opFadeWait": 0,
      "opFadeInEnable": 1,
      "opFadeIn": 15,
      "opFadeColR": 1,
      "opFadeColG": 1,
      "opFadeColB": 1,
      "edFadeOutEnable": 0,
      "edFadeOut": 0,
      "edFadeWait": 0,
      "edFadeInEnable": 0,
      "edFadeIn": 0,
      "edFadeColR": 0,
      "edFadeColG": 0,
      "edFadeColB": 0,
      "stFormID": 0,
      "edFormID": 0,
      "opBgm": 0,
      "edBgm": 0,
      "hideNpc": 0,
      "hideEne": 0,
      "hideMob": 0,
      "hideMap": 1,
      "outsiderOpt": 0,
      "outsiderEnable": 0,
      "outsiderType": 1,
      "outsiderX": 0.0,
      "outsiderY": 0.0,
      "outsiderZ": 0.0,
      "outsiderR": 0.0,
      "listenType": 0,
      "listenX": 0.0,
      "listenY": 0.0,
      "listenZ": 0.0,
      "nextID": 0,
      "zoneID": 46,
      "zoneX": 0.0,
      "zoneY": 0.0,
      "zoneZ": 0.0,
      "zoneR": 0.0,
      "chapID": 1,
      "linkID": 0,
      "jijiDisp": 0,
      "wpnDisp": 1,
      "colFilterNear": 0,
      "colFilterFar": 0,
      "envSeam": 0,
      "evtLight": "",
      "hood": 1,
      "voice": 1,
      "cssnd": 1,
      "scriptName": "",
      "scriptStartId": 0,
      "toneMap": 0.0,
      "noRetarget": 0
    },
    {
      "$id": 19016,
      "evtName": "bf80200107",
      "mstxt": "blade/bf80200100",
      "setupID": 0,
      "chgStID": 0,
      "chgEdID": 0,
      "category": 4,
      "weather": 0,
      "clock": "",
      "clockStop": 0,
      "cloud": 0,
      "text": 1,
      "opFadeOutEnable": 1,
      "opFadeOut": 10,
      "opFadeWait": 0,
      "opFadeInEnable": 1,
      "opFadeIn": 15,
      "opFadeColR": 1,
      "opFadeColG": 1,
      "opFadeColB": 1,
      "edFadeOutEnable": 0,
      "edFadeOut": 0,
      "edFadeWait": 0,
      "edFadeInEnable": 0,
      "edFadeIn": 0,
      "edFadeColR": 0,
      "edFadeColG": 0,
      "edFadeColB": 0,
      "stFormID": 0,
      "edFormID": 0,
      "opBgm": 0,
      "edBgm": 0,
      "hideNpc": 0,
      "hideEne": 0,
      "hideMob": 0,
      "hideMap": 1,
      "outsiderOpt": 0,
      "outsiderEnable": 0,
      "outsiderType": 1,
      "outsiderX": 0.0,
      "outsiderY": 0.0,
      "outsiderZ": 0.0,
      "outsiderR": 0.0,
      "listenType": 0,
      "listenX": 0.0,
      "listenY": 0.0,
      "listenZ": 0.0,
      "nextID": 0,
      "zoneID": 46,
      "zoneX": 0.0,
      "zoneY": 0.0,
      "zoneZ": 0.0,
      "zoneR": 0.0,
      "chapID": 1,
      "linkID": 0,
      "jijiDisp": 0,
      "wpnDisp": 1,
      "colFilterNear": 0,
      "colFilterFar": 0,
      "envSeam": 0,
      "evtLight": "",
      "hood": 1,
      "voice": 1,
      "cssnd": 1,
      "scriptName": "",
      "scriptStartId": 0,
      "toneMap": 0.0,
      "noRetarget": 0
    },
    {
      "$id": 19017,
      "evtName": "bf80200201",
      "mstxt": "blade/bf80200200",
      "setupID": 0,
      "chgStID": 0,
      "chgEdID": 0,
      "category": 4,
      "weather": 0,
      "clock": "",
      "clockStop": 0,
      "cloud": 0,
      "text": 1,
      "opFadeOutEnable": 1,
      "opFadeOut": 10,
      "opFadeWait": 0,
      "opFadeInEnable": 1,
      "opFadeIn": 15,
      "opFadeColR": 1,
      "opFadeColG": 1,
      "opFadeColB": 1,
      "edFadeOutEnable": 0,
      "edFadeOut": 0,
      "edFadeWait": 0,
      "edFadeInEnable": 0,
      "edFadeIn": 0,
      "edFadeColR": 0,
      "edFadeColG": 0,
      "edFadeColB": 0,
      "stFormID": 0,
      "edFormID": 0,
      "opBgm": 0,
      "edBgm": 0,
      "hideNpc": 0,
      "hideEne": 0,
      "hideMob": 0,
      "hideMap": 1,
      "outsiderOpt": 0,
      "outsiderEnable": 0,
      "outsiderType": 1,
      "outsiderX": 0.0,
      "outsiderY": 0.0,
      "outsiderZ": 0.0,
      "outsiderR": 0.0,
      "listenType": 0,
      "listenX": 0.0,
      "listenY": 0.0,
      "listenZ": 0.0,
      "nextID": 0,
      "zoneID": 46,
      "zoneX": 0.0,
      "zoneY": 0.0,
      "zoneZ": 0.0,
      "zoneR": 0.0,
      "chapID": 1,
      "linkID": 0,
      "jijiDisp": 0,
      "wpnDisp": 1,
      "colFilterNear": 0,
      "colFilterFar": 0,
      "envSeam": 0,
      "evtLight": "",
      "hood": 1,
      "voice": 1,
      "cssnd": 1,
      "scriptName": "",
      "scriptStartId": 0,
      "toneMap": 0.0,
      "noRetarget": 0
    },
    {
      "$id": 19018,
      "evtName": "bf80200202",
      "mstxt": "blade/bf80200200",
      "setupID": 0,
      "chgStID": 0,
      "chgEdID": 0,
      "category": 4,
      "weather": 0,
      "clock": "",
      "clockStop": 0,
      "cloud": 0,
      "text": 1,
      "opFadeOutEnable": 1,
      "opFadeOut": 10,
      "opFadeWait": 0,
      "opFadeInEnable": 1,
      "opFadeIn": 15,
      "opFadeColR": 1,
      "opFadeColG": 1,
      "opFadeColB": 1,
      "edFadeOutEnable": 0,
      "edFadeOut": 0,
      "edFadeWait": 0,
      "edFadeInEnable": 0,
      "edFadeIn": 0,
      "edFadeColR": 0,
      "edFadeColG": 0,
      "edFadeColB": 0,
      "stFormID": 0,
      "edFormID": 0,
      "opBgm": 0,
      "edBgm": 0,
      "hideNpc": 0,
      "hideEne": 0,
      "hideMob": 0,
      "hideMap": 1,
      "outsiderOpt": 0,
      "outsiderEnable": 0,
      "outsiderType": 1,
      "outsiderX": 0.0,
      "outsiderY": 0.0,
      "outsiderZ": 0.0,
      "outsiderR": 0.0,
      "listenType": 0,
      "listenX": 0.0,
      "listenY": 0.0,
      "listenZ": 0.0,
      "nextID": 0,
      "zoneID": 46,
      "zoneX": 0.0,
      "zoneY": 0.0,
      "zoneZ": 0.0,
      "zoneR": 0.0,
      "chapID": 1,
      "linkID": 0,
      "jijiDisp": 0,
      "wpnDisp": 1,
      "colFilterNear": 0,
      "colFilterFar": 0,
      "envSeam": 0,
      "evtLight": "",
      "hood": 1,
      "voice": 1,
      "cssnd": 1,
      "scriptName": "",
      "scriptStartId": 0,
      "toneMap": 0.0,
      "noRetarget": 0
    },
    {
      "$id": 19019,
      "evtName": "bf80200203",
      "mstxt": "blade/bf80200200",
      "setupID": 0,
      "chgStID": 0,
      "chgEdID": 0,
      "category": 4,
      "weather": 0,
      "clock": "",
      "clockStop": 0,
      "cloud": 0,
      "text": 1,
      "opFadeOutEnable": 1,
      "opFadeOut": 10,
      "opFadeWait": 0,
      "opFadeInEnable": 1,
      "opFadeIn": 15,
      "opFadeColR": 1,
      "opFadeColG": 1,
      "opFadeColB": 1,
      "edFadeOutEnable": 0,
      "edFadeOut": 0,
      "edFadeWait": 0,
      "edFadeInEnable": 0,
      "edFadeIn": 0,
      "edFadeColR": 0,
      "edFadeColG": 0,
      "edFadeColB": 0,
      "stFormID": 0,
      "edFormID": 0,
      "opBgm": 0,
      "edBgm": 0,
      "hideNpc": 0,
      "hideEne": 0,
      "hideMob": 0,
      "hideMap": 1,
      "outsiderOpt": 0,
      "outsiderEnable": 0,
      "outsiderType": 1,
      "outsiderX": 0.0,
      "outsiderY": 0.0,
      "outsiderZ": 0.0,
      "outsiderR": 0.0,
      "listenType": 0,
      "listenX": 0.0,
      "listenY": 0.0,
      "listenZ": 0.0,
      "nextID": 0,
      "zoneID": 46,
      "zoneX": 0.0,
      "zoneY": 0.0,
      "zoneZ": 0.0,
      "zoneR": 0.0,
      "chapID": 1,
      "linkID": 0,
      "jijiDisp": 0,
      "wpnDisp": 1,
      "colFilterNear": 0,
      "colFilterFar": 0,
      "envSeam": 0,
      "evtLight": "",
      "hood": 1,
      "voice": 1,
      "cssnd": 1,
      "scriptName": "",
      "scriptStartId": 0,
      "toneMap": 0.0,
      "noRetarget": 0
    },
    {
      "$id": 19020,
      "evtName": "bf80200204",
      "mstxt": "blade/bf80200200",
      "setupID": 0,
      "chgStID": 0,
      "chgEdID": 0,
      "category": 4,
      "weather": 0,
      "clock": "",
      "clockStop": 0,
      "cloud": 0,
      "text": 1,
      "opFadeOutEnable": 1,
      "opFadeOut": 10,
      "opFadeWait": 0,
      "opFadeInEnable": 1,
      "opFadeIn": 15,
      "opFadeColR": 1,
      "opFadeColG": 1,
      "opFadeColB": 1,
      "edFadeOutEnable": 0,
      "edFadeOut": 0,
      "edFadeWait": 0,
      "edFadeInEnable": 0,
      "edFadeIn": 0,
      "edFadeColR": 0,
      "edFadeColG": 0,
      "edFadeColB": 0,
      "stFormID": 0,
      "edFormID": 0,
      "opBgm": 0,
      "edBgm": 0,
      "hideNpc": 0,
      "hideEne": 0,
      "hideMob": 0,
      "hideMap": 1,
      "outsiderOpt": 0,
      "outsiderEnable": 0,
      "outsiderType": 1,
      "outsiderX": 0.0,
      "outsiderY": 0.0,
      "outsiderZ": 0.0,
      "outsiderR": 0.0,
      "listenType": 0,
      "listenX": 0.0,
      "listenY": 0.0,
      "listenZ": 0.0,
      "nextID": 0,
      "zoneID": 46,
      "zoneX": 0.0,
      "zoneY": 0.0,
      "zoneZ": 0.0,
      "zoneR": 0.0,
      "chapID": 1,
      "linkID": 0,
      "jijiDisp": 0,
      "wpnDisp": 1,
      "colFilterNear": 0,
      "colFilterFar": 0,
      "envSeam": 0,
      "evtLight": "",
      "hood": 1,
      "voice": 1,
      "cssnd": 1,
      "scriptName": "",
      "scriptStartId": 0,
      "toneMap": 0.0,
      "noRetarget": 0
    },
    {
      "$id": 19021,
      "evtName": "bf80200205",
      "mstxt": "blade/bf80200200",
      "setupID": 0,
      "chgStID": 0,
      "chgEdID": 0,
      "category": 4,
      "weather": 0,
      "clock": "",
      "clockStop": 0,
      "cloud": 0,
      "text": 1,
      "opFadeOutEnable": 1,
      "opFadeOut": 10,
      "opFadeWait": 0,
      "opFadeInEnable": 1,
      "opFadeIn": 15,
      "opFadeColR": 1,
      "opFadeColG": 1,
      "opFadeColB": 1,
      "edFadeOutEnable": 0,
      "edFadeOut": 0,
      "edFadeWait": 0,
      "edFadeInEnable": 0,
      "edFadeIn": 0,
      "edFadeColR": 0,
      "edFadeColG": 0,
      "edFadeColB": 0,
      "stFormID": 0,
      "edFormID": 0,
      "opBgm": 0,
      "edBgm": 0,
      "hideNpc": 0,
      "hideEne": 0,
      "hideMob": 0,
      "hideMap": 1,
      "outsiderOpt": 0,
      "outsiderEnable": 0,
      "outsiderType": 1,
      "outsiderX": 0.0,
      "outsiderY": 0.0,
      "outsiderZ": 0.0,
      "outsiderR": 0.0,
      "listenType": 0,
      "listenX": 0.0,
      "listenY": 0.0,
      "listenZ": 0.0,
      "nextID": 0,
      "zoneID": 46,
      "zoneX": 0.0,
      "zoneY": 0.0,
      "zoneZ": 0.0,
      "zoneR": 0.0,
      "chapID": 1,
      "linkID": 0,
      "jijiDisp": 0,
      "wpnDisp": 1,
      "colFilterNear": 0,
      "colFilterFar": 0,
      "envSeam": 0,
      "evtLight": "",
      "hood": 1,
      "voice": 1,
      "cssnd": 1,
      "scriptName": "",
      "scriptStartId": 0,
      "toneMap": 0.0,
      "noRetarget": 0
    },
    {
      "$id": 19022,
      "evtName": "bf80200206",
      "mstxt": "blade/bf80200200",
      "setupID": 0,
      "chgStID": 0,
      "chgEdID": 0,
      "category": 4,
      "weather": 0,
      "clock": "",
      "clockStop": 0,
      "cloud": 0,
      "text": 1,
      "opFadeOutEnable": 1,
      "opFadeOut": 10,
      "opFadeWait": 0,
      "opFadeInEnable": 1,
      "opFadeIn": 15,
      "opFadeColR": 1,
      "opFadeColG": 1,
      "opFadeColB": 1,
      "edFadeOutEnable": 0,
      "edFadeOut": 0,
      "edFadeWait": 0,
      "edFadeInEnable": 0,
      "edFadeIn": 0,
      "edFadeColR": 0,
      "edFadeColG": 0,
      "edFadeColB": 0,
      "stFormID": 0,
      "edFormID": 0,
      "opBgm": 0,
      "edBgm": 0,
      "hideNpc": 0,
      "hideEne": 0,
      "hideMob": 0,
      "hideMap": 1,
      "outsiderOpt": 0,
      "outsiderEnable": 0,
      "outsiderType": 1,
      "outsiderX": 0.0,
      "outsiderY": 0.0,
      "outsiderZ": 0.0,
      "outsiderR": 0.0,
      "listenType": 0,
      "listenX": 0.0,
      "listenY": 0.0,
      "listenZ": 0.0,
      "nextID": 0,
      "zoneID": 46,
      "zoneX": 0.0,
      "zoneY": 0.0,
      "zoneZ": 0.0,
      "zoneR": 0.0,
      "chapID": 1,
      "linkID": 0,
      "jijiDisp": 0,
      "wpnDisp": 1,
      "colFilterNear": 0,
      "colFilterFar": 0,
      "envSeam": 0,
      "evtLight": "",
      "hood": 1,
      "voice": 1,
      "cssnd": 1,
      "scriptName": "",
      "scriptStartId": 0,
      "toneMap": 0.0,
      "noRetarget": 0
    },
    {
      "$id": 19023,
      "evtName": "bf80200207",
      "mstxt": "blade/bf80200200",
      "setupID": 0,
      "chgStID": 0,
      "chgEdID": 0,
      "category": 4,
      "weather": 0,
      "clock": "",
      "clockStop": 0,
      "cloud": 0,
      "text": 1,
      "opFadeOutEnable": 1,
      "opFadeOut": 10,
      "opFadeWait": 0,
      "opFadeInEnable": 1,
      "opFadeIn": 15,
      "opFadeColR": 1,
      "opFadeColG": 1,
      "opFadeColB": 1,
      "edFadeOutEnable": 0,
      "edFadeOut": 0,
      "edFadeWait": 0,
      "edFadeInEnable": 0,
      "edFadeIn": 0,
      "edFadeColR": 0,
      "edFadeColG": 0,
      "edFadeColB": 0,
      "stFormID": 0,
      "edFormID": 0,
      "opBgm": 0,
      "edBgm": 0,
      "hideNpc": 0,
      "hideEne": 0,
      "hideMob": 0,
      "hideMap": 1,
      "outsiderOpt": 0,
      "outsiderEnable": 0,
      "outsiderType": 1,
      "outsiderX": 0.0,
      "outsiderY": 0.0,
      "outsiderZ": 0.0,
      "outsiderR": 0.0,
      "listenType": 0,
      "listenX": 0.0,
      "listenY": 0.0,
      "listenZ": 0.0,
      "nextID": 0,
      "zoneID": 46,
      "zoneX": 0.0,
      "zoneY": 0.0,
      "zoneZ": 0.0,
      "zoneR": 0.0,
      "chapID": 1,
      "linkID": 0,
      "jijiDisp": 0,
      "wpnDisp": 1,
      "colFilterNear": 0,
      "colFilterFar": 0,
      "envSeam": 0,
      "evtLight": "",
      "hood": 1,
      "voice": 1,
      "cssnd": 1,
      "scriptName": "",
      "scriptStartId": 0,
      "toneMap": 0.0,
      "noRetarget": 0
    },
    {
      "$id": 19024,
      "evtName": "bf80200301",
      "mstxt": "blade/bf80200300",
      "setupID": 0,
      "chgStID": 0,
      "chgEdID": 0,
      "category": 4,
      "weather": 0,
      "clock": "",
      "clockStop": 0,
      "cloud": 0,
      "text": 1,
      "opFadeOutEnable": 1,
      "opFadeOut": 10,
      "opFadeWait": 0,
      "opFadeInEnable": 1,
      "opFadeIn": 15,
      "opFadeColR": 1,
      "opFadeColG": 1,
      "opFadeColB": 1,
      "edFadeOutEnable": 0,
      "edFadeOut": 0,
      "edFadeWait": 0,
      "edFadeInEnable": 0,
      "edFadeIn": 0,
      "edFadeColR": 0,
      "edFadeColG": 0,
      "edFadeColB": 0,
      "stFormID": 0,
      "edFormID": 0,
      "opBgm": 0,
      "edBgm": 0,
      "hideNpc": 0,
      "hideEne": 0,
      "hideMob": 0,
      "hideMap": 1,
      "outsiderOpt": 0,
      "outsiderEnable": 0,
      "outsiderType": 1,
      "outsiderX": 0.0,
      "outsiderY": 0.0,
      "outsiderZ": 0.0,
      "outsiderR": 0.0,
      "listenType": 0,
      "listenX": 0.0,
      "listenY": 0.0,
      "listenZ": 0.0,
      "nextID": 0,
      "zoneID": 46,
      "zoneX": 0.0,
      "zoneY": 0.0,
      "zoneZ": 0.0,
      "zoneR": 0.0,
      "chapID": 1,
      "linkID": 0,
      "jijiDisp": 0,
      "wpnDisp": 1,
      "colFilterNear": 0,
      "colFilterFar": 0,
      "envSeam": 0,
      "evtLight": "",
      "hood": 1,
      "voice": 1,
      "cssnd": 1,
      "scriptName": "",
      "scriptStartId": 0,
      "toneMap": 0.0,
      "noRetarget": 0
    },
    {
      "$id": 19025,
      "evtName": "bf80200302",
      "mstxt": "blade/bf80200300",
      "setupID": 0,
      "chgStID": 0,
      "chgEdID": 0,
      "category": 4,
      "weather": 0,
      "clock": "",
      "clockStop": 0,
      "cloud": 0,
      "text": 1,
      "opFadeOutEnable": 1,
      "opFadeOut": 10,
      "opFadeWait": 0,
      "opFadeInEnable": 1,
      "opFadeIn": 15,
      "opFadeColR": 1,
      "opFadeColG": 1,
      "opFadeColB": 1,
      "edFadeOutEnable": 0,
      "edFadeOut": 0,
      "edFadeWait": 0,
      "edFadeInEnable": 0,
      "edFadeIn": 0,
      "edFadeColR": 0,
      "edFadeColG": 0,
      "edFadeColB": 0,
      "stFormID": 0,
      "edFormID": 0,
      "opBgm": 0,
      "edBgm": 0,
      "hideNpc": 0,
      "hideEne": 0,
      "hideMob": 0,
      "hideMap": 1,
      "outsiderOpt": 0,
      "outsiderEnable": 0,
      "outsiderType": 1,
      "outsiderX": 0.0,
      "outsiderY": 0.0,
      "outsiderZ": 0.0,
      "outsiderR": 0.0,
      "listenType": 0,
      "listenX": 0.0,
      "listenY": 0.0,
      "listenZ": 0.0,
      "nextID": 0,
      "zoneID": 46,
      "zoneX": 0.0,
      "zoneY": 0.0,
      "zoneZ": 0.0,
      "zoneR": 0.0,
      "chapID": 1,
      "linkID": 0,
      "jijiDisp": 0,
      "wpnDisp": 1,
      "colFilterNear": 0,
      "colFilterFar": 0,
      "envSeam": 0,
      "evtLight": "",
      "hood": 1,
      "voice": 1,
      "cssnd": 1,
      "scriptName": "",
      "scriptStartId": 0,
      "toneMap": 0.0,
      "noRetarget": 0
    },
    {
      "$id": 19026,
      "evtName": "bf80200303",
      "mstxt": "blade/bf80200300",
      "setupID": 0,
      "chgStID": 0,
      "chgEdID": 0,
      "category": 4,
      "weather": 0,
      "clock": "",
      "clockStop": 0,
      "cloud": 0,
      "text": 1,
      "opFadeOutEnable": 1,
      "opFadeOut": 10,
      "opFadeWait": 0,
      "opFadeInEnable": 1,
      "opFadeIn": 15,
      "opFadeColR": 1,
      "opFadeColG": 1,
      "opFadeColB": 1,
      "edFadeOutEnable": 0,
      "edFadeOut": 0,
      "edFadeWait": 0,
      "edFadeInEnable": 0,
      "edFadeIn": 0,
      "edFadeColR": 0,
      "edFadeColG": 0,
      "edFadeColB": 0,
      "stFormID": 0,
      "edFormID": 0,
      "opBgm": 0,
      "edBgm": 0,
      "hideNpc": 0,
      "hideEne": 0,
      "hideMob": 0,
      "hideMap": 1,
      "outsiderOpt": 0,
      "outsiderEnable": 0,
      "outsiderType": 1,
      "outsiderX": 0.0,
      "outsiderY": 0.0,
      "outsiderZ": 0.0,
      "outsiderR": 0.0,
      "listenType": 0,
      "listenX": 0.0,
      "listenY": 0.0,
      "listenZ": 0.0,
      "nextID": 0,
      "zoneID": 46,
      "zoneX": 0.0,
      "zoneY": 0.0,
      "zoneZ": 0.0,
      "zoneR": 0.0,
      "chapID": 1,
      "linkID": 0,
      "jijiDisp": 0,
      "wpnDisp": 1,
      "colFilterNear": 0,
      "colFilterFar": 0,
      "envSeam": 0,
      "evtLight": "",
      "hood": 1,
      "voice": 1,
      "cssnd": 1,
      "scriptName": "",
      "scriptStartId": 0,
      "toneMap": 0.0,
      "noRetarget": 0
    },
    {
      "$id": 19027,
      "evtName": "bf80200304",
      "mstxt": "blade/bf80200300",
      "setupID": 0,
      "chgStID": 0,
      "chgEdID": 0,
      "category": 4,
      "weather": 0,
      "clock": "",
      "clockStop": 0,
      "cloud": 0,
      "text": 1,
      "opFadeOutEnable": 1,
      "opFadeOut": 10,
      "opFadeWait": 0,
      "opFadeInEnable": 1,
      "opFadeIn": 15,
      "opFadeColR": 1,
      "opFadeColG": 1,
      "opFadeColB": 1,
      "edFadeOutEnable": 0,
      "edFadeOut": 0,
      "edFadeWait": 0,
      "edFadeInEnable": 0,
      "edFadeIn": 0,
      "edFadeColR": 0,
      "edFadeColG": 0,
      "edFadeColB": 0,
      "stFormID": 0,
      "edFormID": 0,
      "opBgm": 0,
      "edBgm": 0,
      "hideNpc": 0,
      "hideEne": 0,
      "hideMob": 0,
      "hideMap": 1,
      "outsiderOpt": 0,
      "outsiderEnable": 0,
      "outsiderType": 1,
      "outsiderX": 0.0,
      "outsiderY": 0.0,
      "outsiderZ": 0.0,
      "outsiderR": 0.0,
      "listenType": 0,
      "listenX": 0.0,
      "listenY": 0.0,
      "listenZ": 0.0,
      "nextID": 0,
      "zoneID": 46,
      "zoneX": 0.0,
      "zoneY": 0.0,
      "zoneZ": 0.0,
      "zoneR": 0.0,
      "chapID": 1,
      "linkID": 0,
      "jijiDisp": 0,
      "wpnDisp": 1,
      "colFilterNear": 0,
      "colFilterFar": 0,
      "envSeam": 0,
      "evtLight": "",
      "hood": 1,
      "voice": 1,
      "cssnd": 1,
      "scriptName": "",
      "scriptStartId": 0,
      "toneMap": 0.0,
      "noRetarget": 0
    },
    {
      "$id": 19028,
      "evtName": "bf80200305",
      "mstxt": "blade/bf80200300",
      "setupID": 0,
      "chgStID": 0,
      "chgEdID": 0,
      "category": 4,
      "weather": 0,
      "clock": "",
      "clockStop": 0,
      "cloud": 0,
      "text": 1,
      "opFadeOutEnable": 1,
      "opFadeOut": 10,
      "opFadeWait": 0,
      "opFadeInEnable": 1,
      "opFadeIn": 15,
      "opFadeColR": 1,
      "opFadeColG": 1,
      "opFadeColB": 1,
      "edFadeOutEnable": 0,
      "edFadeOut": 0,
      "edFadeWait": 0,
      "edFadeInEnable": 0,
      "edFadeIn": 0,
      "edFadeColR": 0,
      "edFadeColG": 0,
      "edFadeColB": 0,
      "stFormID": 0,
      "edFormID": 0,
      "opBgm": 0,
      "edBgm": 0,
      "hideNpc": 0,
      "hideEne": 0,
      "hideMob": 0,
      "hideMap": 1,
      "outsiderOpt": 0,
      "outsiderEnable": 0,
      "outsiderType": 1,
      "outsiderX": 0.0,
      "outsiderY": 0.0,
      "outsiderZ": 0.0,
      "outsiderR": 0.0,
      "listenType": 0,
      "listenX": 0.0,
      "listenY": 0.0,
      "listenZ": 0.0,
      "nextID": 0,
      "zoneID": 46,
      "zoneX": 0.0,
      "zoneY": 0.0,
      "zoneZ": 0.0,
      "zoneR": 0.0,
      "chapID": 1,
      "linkID": 0,
      "jijiDisp": 0,
      "wpnDisp": 1,
      "colFilterNear": 0,
      "colFilterFar": 0,
      "envSeam": 0,
      "evtLight": "",
      "hood": 1,
      "voice": 1,
      "cssnd": 1,
      "scriptName": "",
      "scriptStartId": 0,
      "toneMap": 0.0,
      "noRetarget": 0
    },
    {
      "$id": 19029,
      "evtName": "bf80200306",
      "mstxt": "blade/bf80200300",
      "setupID": 0,
      "chgStID": 0,
      "chgEdID": 0,
      "category": 4,
      "weather": 0,
      "clock": "",
      "clockStop": 0,
      "cloud": 0,
      "text": 1,
      "opFadeOutEnable": 1,
      "opFadeOut": 10,
      "opFadeWait": 0,
      "opFadeInEnable": 1,
      "opFadeIn": 15,
      "opFadeColR": 1,
      "opFadeColG": 1,
      "opFadeColB": 1,
      "edFadeOutEnable": 0,
      "edFadeOut": 0,
      "edFadeWait": 0,
      "edFadeInEnable": 0,
      "edFadeIn": 0,
      "edFadeColR": 0,
      "edFadeColG": 0,
      "edFadeColB": 0,
      "stFormID": 0,
      "edFormID": 0,
      "opBgm": 0,
      "edBgm": 0,
      "hideNpc": 0,
      "hideEne": 0,
      "hideMob": 0,
      "hideMap": 1,
      "outsiderOpt": 0,
      "outsiderEnable": 0,
      "outsiderType": 1,
      "outsiderX": 0.0,
      "outsiderY": 0.0,
      "outsiderZ": 0.0,
      "outsiderR": 0.0,
      "listenType": 0,
      "listenX": 0.0,
      "listenY": 0.0,
      "listenZ": 0.0,
      "nextID": 0,
      "zoneID": 46,
      "zoneX": 0.0,
      "zoneY": 0.0,
      "zoneZ": 0.0,
      "zoneR": 0.0,
      "chapID": 1,
      "linkID": 0,
      "jijiDisp": 0,
      "wpnDisp": 1,
      "colFilterNear": 0,
      "colFilterFar": 0,
      "envSeam": 0,
      "evtLight": "",
      "hood": 1,
      "voice": 1,
      "cssnd": 1,
      "scriptName": "",
      "scriptStartId": 0,
      "toneMap": 0.0,
      "noRetarget": 0
    },
    {
      "$id": 19030,
      "evtName": "bf80200307",
      "mstxt": "blade/bf80200300",
      "setupID": 0,
      "chgStID": 0,
      "chgEdID": 0,
      "category": 4,
      "weather": 0,
      "clock": "",
      "clockStop": 0,
      "cloud": 0,
      "text": 1,
      "opFadeOutEnable": 1,
      "opFadeOut": 10,
      "opFadeWait": 0,
      "opFadeInEnable": 1,
      "opFadeIn": 15,
      "opFadeColR": 1,
      "opFadeColG": 1,
      "opFadeColB": 1,
      "edFadeOutEnable": 0,
      "edFadeOut": 0,
      "edFadeWait": 0,
      "edFadeInEnable": 0,
      "edFadeIn": 0,
      "edFadeColR": 0,
      "edFadeColG": 0,
      "edFadeColB": 0,
      "stFormID": 0,
      "edFormID": 0,
      "opBgm": 0,
      "edBgm": 0,
      "hideNpc": 0,
      "hideEne": 0,
      "hideMob": 0,
      "hideMap": 1,
      "outsiderOpt": 0,
      "outsiderEnable": 0,
      "outsiderType": 1,
      "outsiderX": 0.0,
      "outsiderY": 0.0,
      "outsiderZ": 0.0,
      "outsiderR": 0.0,
      "listenType": 0,
      "listenX": 0.0,
      "listenY": 0.0,
      "listenZ": 0.0,
      "nextID": 0,
      "zoneID": 46,
      "zoneX": 0.0,
      "zoneY": 0.0,
      "zoneZ": 0.0,
      "zoneR": 0.0,
      "chapID": 1,
      "linkID": 0,
      "jijiDisp": 0,
      "wpnDisp": 1,
      "colFilterNear": 0,
      "colFilterFar": 0,
      "envSeam": 0,
      "evtLight": "",
      "hood": 1,
      "voice": 1,
      "cssnd": 1,
      "scriptName": "",
      "scriptStartId": 0,
      "toneMap": 0.0,
      "noRetarget": 0
    },
    {
      "$id": 19031,
      "evtName": "bf80200401",
      "mstxt": "blade/bf80200400",
      "setupID": 0,
      "chgStID": 0,
      "chgEdID": 0,
      "category": 4,
      "weather": 0,
      "clock": "",
      "clockStop": 0,
      "cloud": 0,
      "text": 1,
      "opFadeOutEnable": 1,
      "opFadeOut": 10,
      "opFadeWait": 0,
      "opFadeInEnable": 1,
      "opFadeIn": 15,
      "opFadeColR": 1,
      "opFadeColG": 1,
      "opFadeColB": 1,
      "edFadeOutEnable": 0,
      "edFadeOut": 0,
      "edFadeWait": 0,
      "edFadeInEnable": 0,
      "edFadeIn": 0,
      "edFadeColR": 0,
      "edFadeColG": 0,
      "edFadeColB": 0,
      "stFormID": 0,
      "edFormID": 0,
      "opBgm": 0,
      "edBgm": 0,
      "hideNpc": 0,
      "hideEne": 0,
      "hideMob": 0,
      "hideMap": 1,
      "outsiderOpt": 0,
      "outsiderEnable": 0,
      "outsiderType": 1,
      "outsiderX": 0.0,
      "outsiderY": 0.0,
      "outsiderZ": 0.0,
      "outsiderR": 0.0,
      "listenType": 0,
      "listenX": 0.0,
      "listenY": 0.0,
      "listenZ": 0.0,
      "nextID": 0,
      "zoneID": 46,
      "zoneX": 0.0,
      "zoneY": 0.0,
      "zoneZ": 0.0,
      "zoneR": 0.0,
      "chapID": 1,
      "linkID": 0,
      "jijiDisp": 0,
      "wpnDisp": 1,
      "colFilterNear": 0,
      "colFilterFar": 0,
      "envSeam": 0,
      "evtLight": "",
      "hood": 1,
      "voice": 1,
      "cssnd": 1,
      "scriptName": "",
      "scriptStartId": 0,
      "toneMap": 0.0,
      "noRetarget": 0
    },
    {
      "$id": 19032,
      "evtName": "bf80300101",
      "mstxt": "blade/bf80300101",
      "setupID": 0,
      "chgStID": 0,
      "chgEdID": 0,
      "category": 4,
      "weather": 0,
      "clock": "",
      "clockStop": 0,
      "cloud": 0,
      "text": 1,
      "opFadeOutEnable": 1,
      "opFadeOut": 10,
      "opFadeWait": 0,
      "opFadeInEnable": 1,
      "opFadeIn": 15,
      "opFadeColR": 1,
      "opFadeColG": 1,
      "opFadeColB": 1,
      "edFadeOutEnable": 0,
      "edFadeOut": 0,
      "edFadeWait": 0,
      "edFadeInEnable": 0,
      "edFadeIn": 0,
      "edFadeColR": 0,
      "edFadeColG": 0,
      "edFadeColB": 0,
      "stFormID": 0,
      "edFormID": 0,
      "opBgm": 0,
      "edBgm": 0,
      "hideNpc": 0,
      "hideEne": 0,
      "hideMob": 0,
      "hideMap": 1,
      "outsiderOpt": 0,
      "outsiderEnable": 0,
      "outsiderType": 1,
      "outsiderX": 0.0,
      "outsiderY": 0.0,
      "outsiderZ": 0.0,
      "outsiderR": 0.0,
      "listenType": 0,
      "listenX": 0.0,
      "listenY": 0.0,
      "listenZ": 0.0,
      "nextID": 0,
      "zoneID": 46,
      "zoneX": 0.0,
      "zoneY": 0.0,
      "zoneZ": 0.0,
      "zoneR": 0.0,
      "chapID": 1,
      "linkID": 0,
      "jijiDisp": 0,
      "wpnDisp": 1,
      "colFilterNear": 0,
      "colFilterFar": 0,
      "envSeam": 0,
      "evtLight": "",
      "hood": 1,
      "voice": 1,
      "cssnd": 1,
      "scriptName": "",
      "scriptStartId": 0,
      "toneMap": 0.0,
      "noRetarget": 0
    },
    {
      "$id": 19033,
      "evtName": "bf80300201",
      "mstxt": "blade/bf80300201",
      "setupID": 0,
      "chgStID": 0,
      "chgEdID": 0,
      "category": 4,
      "weather": 0,
      "clock": "",
      "clockStop": 0,
      "cloud": 0,
      "text": 1,
      "opFadeOutEnable": 1,
      "opFadeOut": 10,
      "opFadeWait": 0,
      "opFadeInEnable": 1,
      "opFadeIn": 15,
      "opFadeColR": 1,
      "opFadeColG": 1,
      "opFadeColB": 1,
      "edFadeOutEnable": 0,
      "edFadeOut": 0,
      "edFadeWait": 0,
      "edFadeInEnable": 0,
      "edFadeIn": 0,
      "edFadeColR": 0,
      "edFadeColG": 0,
      "edFadeColB": 0,
      "stFormID": 0,
      "edFormID": 0,
      "opBgm": 0,
      "edBgm": 0,
      "hideNpc": 0,
      "hideEne": 0,
      "hideMob": 0,
      "hideMap": 1,
      "outsiderOpt": 0,
      "outsiderEnable": 0,
      "outsiderType": 1,
      "outsiderX": 0.0,
      "outsiderY": 0.0,
      "outsiderZ": 0.0,
      "outsiderR": 0.0,
      "listenType": 0,
      "listenX": 0.0,
      "listenY": 0.0,
      "listenZ": 0.0,
      "nextID": 0,
      "zoneID": 46,
      "zoneX": 0.0,
      "zoneY": 0.0,
      "zoneZ": 0.0,
      "zoneR": 0.0,
      "chapID": 1,
      "linkID": 0,
      "jijiDisp": 0,
      "wpnDisp": 1,
      "colFilterNear": 0,
      "colFilterFar": 0,
      "envSeam": 0,
      "evtLight": "",
      "hood": 1,
      "voice": 1,
      "cssnd": 1,
      "scriptName": "",
      "scriptStartId": 0,
      "toneMap": 0.0,
      "noRetarget": 0
    },
    {
      "$id": 19034,
      "evtName": "bf80300301",
      "mstxt": "blade/bf80300301",
      "setupID": 0,
      "chgStID": 0,
      "chgEdID": 0,
      "category": 4,
      "weather": 0,
      "clock": "",
      "clockStop": 0,
      "cloud": 0,
      "text": 1,
      "opFadeOutEnable": 1,
      "opFadeOut": 10,
      "opFadeWait": 0,
      "opFadeInEnable": 1,
      "opFadeIn": 15,
      "opFadeColR": 1,
      "opFadeColG": 1,
      "opFadeColB": 1,
      "edFadeOutEnable": 0,
      "edFadeOut": 0,
      "edFadeWait": 0,
      "edFadeInEnable": 0,
      "edFadeIn": 0,
      "edFadeColR": 0,
      "edFadeColG": 0,
      "edFadeColB": 0,
      "stFormID": 0,
      "edFormID": 0,
      "opBgm": 0,
      "edBgm": 0,
      "hideNpc": 0,
      "hideEne": 0,
      "hideMob": 0,
      "hideMap": 1,
      "outsiderOpt": 0,
      "outsiderEnable": 0,
      "outsiderType": 1,
      "outsiderX": 0.0,
      "outsiderY": 0.0,
      "outsiderZ": 0.0,
      "outsiderR": 0.0,
      "listenType": 0,
      "listenX": 0.0,
      "listenY": 0.0,
      "listenZ": 0.0,
      "nextID": 0,
      "zoneID": 46,
      "zoneX": 0.0,
      "zoneY": 0.0,
      "zoneZ": 0.0,
      "zoneR": 0.0,
      "chapID": 1,
      "linkID": 0,
      "jijiDisp": 0,
      "wpnDisp": 1,
      "colFilterNear": 0,
      "colFilterFar": 0,
      "envSeam": 0,
      "evtLight": "",
      "hood": 1,
      "voice": 1,
      "cssnd": 1,
      "scriptName": "",
      "scriptStartId": 0,
      "toneMap": 0.0,
      "noRetarget": 0
    },
    {
      "$id": 19035,
      "evtName": "bf80300401",
      "mstxt": "blade/bf80300401",
      "setupID": 0,
      "chgStID": 0,
      "chgEdID": 0,
      "category": 4,
      "weather": 0,
      "clock": "",
      "clockStop": 0,
      "cloud": 0,
      "text": 1,
      "opFadeOutEnable": 1,
      "opFadeOut": 10,
      "opFadeWait": 0,
      "opFadeInEnable": 1,
      "opFadeIn": 15,
      "opFadeColR": 1,
      "opFadeColG": 1,
      "opFadeColB": 1,
      "edFadeOutEnable": 0,
      "edFadeOut": 0,
      "edFadeWait": 0,
      "edFadeInEnable": 0,
      "edFadeIn": 0,
      "edFadeColR": 0,
      "edFadeColG": 0,
      "edFadeColB": 0,
      "stFormID": 0,
      "edFormID": 0,
      "opBgm": 0,
      "edBgm": 0,
      "hideNpc": 0,
      "hideEne": 0,
      "hideMob": 0,
      "hideMap": 1,
      "outsiderOpt": 0,
      "outsiderEnable": 0,
      "outsiderType": 1,
      "outsiderX": 0.0,
      "outsiderY": 0.0,
      "outsiderZ": 0.0,
      "outsiderR": 0.0,
      "listenType": 0,
      "listenX": 0.0,
      "listenY": 0.0,
      "listenZ": 0.0,
      "nextID": 0,
      "zoneID": 46,
      "zoneX": 0.0,
      "zoneY": 0.0,
      "zoneZ": 0.0,
      "zoneR": 0.0,
      "chapID": 1,
      "linkID": 0,
      "jijiDisp": 0,
      "wpnDisp": 1,
      "colFilterNear": 0,
      "colFilterFar": 0,
      "envSeam": 0,
      "evtLight": "",
      "hood": 1,
      "voice": 1,
      "cssnd": 1,
      "scriptName": "",
      "scriptStartId": 0,
      "toneMap": 0.0,
      "noRetarget": 0
    },
    {
      "$id": 19036,
      "evtName": "bf80300501",
      "mstxt": "blade/bf80300501",
      "setupID": 0,
      "chgStID": 0,
      "chgEdID": 0,
      "category": 4,
      "weather": 0,
      "clock": "",
      "clockStop": 0,
      "cloud": 0,
      "text": 1,
      "opFadeOutEnable": 1,
      "opFadeOut": 10,
      "opFadeWait": 0,
      "opFadeInEnable": 1,
      "opFadeIn": 15,
      "opFadeColR": 1,
      "opFadeColG": 1,
      "opFadeColB": 1,
      "edFadeOutEnable": 0,
      "edFadeOut": 0,
      "edFadeWait": 0,
      "edFadeInEnable": 0,
      "edFadeIn": 0,
      "edFadeColR": 0,
      "edFadeColG": 0,
      "edFadeColB": 0,
      "stFormID": 0,
      "edFormID": 0,
      "opBgm": 0,
      "edBgm": 0,
      "hideNpc": 0,
      "hideEne": 0,
      "hideMob": 0,
      "hideMap": 1,
      "outsiderOpt": 0,
      "outsiderEnable": 0,
      "outsiderType": 1,
      "outsiderX": 0.0,
      "outsiderY": 0.0,
      "outsiderZ": 0.0,
      "outsiderR": 0.0,
      "listenType": 0,
      "listenX": 0.0,
      "listenY": 0.0,
      "listenZ": 0.0,
      "nextID": 0,
      "zoneID": 46,
      "zoneX": 0.0,
      "zoneY": 0.0,
      "zoneZ": 0.0,
      "zoneR": 0.0,
      "chapID": 1,
      "linkID": 0,
      "jijiDisp": 0,
      "wpnDisp": 1,
      "colFilterNear": 0,
      "colFilterFar": 0,
      "envSeam": 0,
      "evtLight": "",
      "hood": 1,
      "voice": 1,
      "cssnd": 1,
      "scriptName": "",
      "scriptStartId": 0,
      "toneMap": 0.0,
      "noRetarget": 0
    },
    {
      "$id": 19037,
      "evtName": "bf80300601",
      "mstxt": "blade/bf80300601",
      "setupID": 0,
      "chgStID": 0,
      "chgEdID": 0,
      "category": 4,
      "weather": 0,
      "clock": "",
      "clockStop": 0,
      "cloud": 0,
      "text": 1,
      "opFadeOutEnable": 1,
      "opFadeOut": 10,
      "opFadeWait": 0,
      "opFadeInEnable": 1,
      "opFadeIn": 15,
      "opFadeColR": 1,
      "opFadeColG": 1,
      "opFadeColB": 1,
      "edFadeOutEnable": 0,
      "edFadeOut": 0,
      "edFadeWait": 0,
      "edFadeInEnable": 0,
      "edFadeIn": 0,
      "edFadeColR": 0,
      "edFadeColG": 0,
      "edFadeColB": 0,
      "stFormID": 0,
      "edFormID": 0,
      "opBgm": 0,
      "edBgm": 0,
      "hideNpc": 0,
      "hideEne": 0,
      "hideMob": 0,
      "hideMap": 1,
      "outsiderOpt": 0,
      "outsiderEnable": 0,
      "outsiderType": 1,
      "outsiderX": 0.0,
      "outsiderY": 0.0,
      "outsiderZ": 0.0,
      "outsiderR": 0.0,
      "listenType": 0,
      "listenX": 0.0,
      "listenY": 0.0,
      "listenZ": 0.0,
      "nextID": 0,
      "zoneID": 46,
      "zoneX": 0.0,
      "zoneY": 0.0,
      "zoneZ": 0.0,
      "zoneR": 0.0,
      "chapID": 1,
      "linkID": 0,
      "jijiDisp": 0,
      "wpnDisp": 1,
      "colFilterNear": 0,
      "colFilterFar": 0,
      "envSeam": 0,
      "evtLight": "",
      "hood": 1,
      "voice": 1,
      "cssnd": 1,
      "scriptName": "",
      "scriptStartId": 0,
      "toneMap": 0.0,
      "noRetarget": 0
    },
    {
      "$id": 19038,
      "evtName": "bf80300701",
      "mstxt": "blade/bf80300701",
      "setupID": 0,
      "chgStID": 0,
      "chgEdID": 0,
      "category": 4,
      "weather": 0,
      "clock": "",
      "clockStop": 0,
      "cloud": 0,
      "text": 1,
      "opFadeOutEnable": 1,
      "opFadeOut": 10,
      "opFadeWait": 0,
      "opFadeInEnable": 1,
      "opFadeIn": 15,
      "opFadeColR": 1,
      "opFadeColG": 1,
      "opFadeColB": 1,
      "edFadeOutEnable": 0,
      "edFadeOut": 0,
      "edFadeWait": 0,
      "edFadeInEnable": 0,
      "edFadeIn": 0,
      "edFadeColR": 0,
      "edFadeColG": 0,
      "edFadeColB": 0,
      "stFormID": 0,
      "edFormID": 0,
      "opBgm": 0,
      "edBgm": 0,
      "hideNpc": 0,
      "hideEne": 0,
      "hideMob": 0,
      "hideMap": 1,
      "outsiderOpt": 0,
      "outsiderEnable": 0,
      "outsiderType": 1,
      "outsiderX": 0.0,
      "outsiderY": 0.0,
      "outsiderZ": 0.0,
      "outsiderR": 0.0,
      "listenType": 0,
      "listenX": 0.0,
      "listenY": 0.0,
      "listenZ": 0.0,
      "nextID": 0,
      "zoneID": 46,
      "zoneX": 0.0,
      "zoneY": 0.0,
      "zoneZ": 0.0,
      "zoneR": 0.0,
      "chapID": 1,
      "linkID": 0,
      "jijiDisp": 0,
      "wpnDisp": 1,
      "colFilterNear": 0,
      "colFilterFar": 0,
      "envSeam": 0,
      "evtLight": "",
      "hood": 1,
      "voice": 1,
      "cssnd": 1,
      "scriptName": "",
      "scriptStartId": 0,
      "toneMap": 0.0,
      "noRetarget": 0
    },
    {
      "$id": 19039,
      "evtName": "bf80300801",
      "mstxt": "blade/bf80300801",
      "setupID": 0,
      "chgStID": 0,
      "chgEdID": 0,
      "category": 4,
      "weather": 0,
      "clock": "",
      "clockStop": 0,
      "cloud": 0,
      "text": 1,
      "opFadeOutEnable": 1,
      "opFadeOut": 10,
      "opFadeWait": 0,
      "opFadeInEnable": 1,
      "opFadeIn": 15,
      "opFadeColR": 1,
      "opFadeColG": 1,
      "opFadeColB": 1,
      "edFadeOutEnable": 0,
      "edFadeOut": 0,
      "edFadeWait": 0,
      "edFadeInEnable": 0,
      "edFadeIn": 0,
      "edFadeColR": 0,
      "edFadeColG": 0,
      "edFadeColB": 0,
      "stFormID": 0,
      "edFormID": 0,
      "opBgm": 0,
      "edBgm": 0,
      "hideNpc": 0,
      "hideEne": 0,
      "hideMob": 0,
      "hideMap": 1,
      "outsiderOpt": 0,
      "outsiderEnable": 0,
      "outsiderType": 1,
      "outsiderX": 0.0,
      "outsiderY": 0.0,
      "outsiderZ": 0.0,
      "outsiderR": 0.0,
      "listenType": 0,
      "listenX": 0.0,
      "listenY": 0.0,
      "listenZ": 0.0,
      "nextID": 0,
      "zoneID": 46,
      "zoneX": 0.0,
      "zoneY": 0.0,
      "zoneZ": 0.0,
      "zoneR": 0.0,
      "chapID": 1,
      "linkID": 0,
      "jijiDisp": 0,
      "wpnDisp": 1,
      "colFilterNear": 0,
      "colFilterFar": 0,
      "envSeam": 0,
      "evtLight": "",
      "hood": 1,
      "voice": 1,
      "cssnd": 1,
      "scriptName": "",
      "scriptStartId": 0,
      "toneMap": 0.0,
      "noRetarget": 0
    },
    {
      "$id": 19040,
      "evtName": "bf80300901",
      "mstxt": "blade/bf80300901",
      "setupID": 0,
      "chgStID": 0,
      "chgEdID": 0,
      "category": 4,
      "weather": 0,
      "clock": "",
      "clockStop": 0,
      "cloud": 0,
      "text": 1,
      "opFadeOutEnable": 1,
      "opFadeOut": 10,
      "opFadeWait": 0,
      "opFadeInEnable": 1,
      "opFadeIn": 15,
      "opFadeColR": 1,
      "opFadeColG": 1,
      "opFadeColB": 1,
      "edFadeOutEnable": 0,
      "edFadeOut": 0,
      "edFadeWait": 0,
      "edFadeInEnable": 0,
      "edFadeIn": 0,
      "edFadeColR": 0,
      "edFadeColG": 0,
      "edFadeColB": 0,
      "stFormID": 0,
      "edFormID": 0,
      "opBgm": 0,
      "edBgm": 0,
      "hideNpc": 0,
      "hideEne": 0,
      "hideMob": 0,
      "hideMap": 1,
      "outsiderOpt": 0,
      "outsiderEnable": 0,
      "outsiderType": 1,
      "outsiderX": 0.0,
      "outsiderY": 0.0,
      "outsiderZ": 0.0,
      "outsiderR": 0.0,
      "listenType": 0,
      "listenX": 0.0,
      "listenY": 0.0,
      "listenZ": 0.0,
      "nextID": 0,
      "zoneID": 46,
      "zoneX": 0.0,
      "zoneY": 0.0,
      "zoneZ": 0.0,
      "zoneR": 0.0,
      "chapID": 1,
      "linkID": 0,
      "jijiDisp": 0,
      "wpnDisp": 1,
      "colFilterNear": 0,
      "colFilterFar": 0,
      "envSeam": 0,
      "evtLight": "",
      "hood": 1,
      "voice": 1,
      "cssnd": 1,
      "scriptName": "",
      "scriptStartId": 0,
      "toneMap": 0.0,
      "noRetarget": 0
    },
    {
      "$id": 19041,
      "evtName": "bf80301001",
      "mstxt": "blade/bf80301001",
      "setupID": 0,
      "chgStID": 0,
      "chgEdID": 0,
      "category": 4,
      "weather": 0,
      "clock": "",
      "clockStop": 0,
      "cloud": 0,
      "text": 1,
      "opFadeOutEnable": 1,
      "opFadeOut": 10,
      "opFadeWait": 0,
      "opFadeInEnable": 1,
      "opFadeIn": 15,
      "opFadeColR": 1,
      "opFadeColG": 1,
      "opFadeColB": 1,
      "edFadeOutEnable": 0,
      "edFadeOut": 0,
      "edFadeWait": 0,
      "edFadeInEnable": 0,
      "edFadeIn": 0,
      "edFadeColR": 0,
      "edFadeColG": 0,
      "edFadeColB": 0,
      "stFormID": 0,
      "edFormID": 0,
      "opBgm": 0,
      "edBgm": 0,
      "hideNpc": 0,
      "hideEne": 0,
      "hideMob": 0,
      "hideMap": 1,
      "outsiderOpt": 0,
      "outsiderEnable": 0,
      "outsiderType": 1,
      "outsiderX": 0.0,
      "outsiderY": 0.0,
      "outsiderZ": 0.0,
      "outsiderR": 0.0,
      "listenType": 0,
      "listenX": 0.0,
      "listenY": 0.0,
      "listenZ": 0.0,
      "nextID": 0,
      "zoneID": 46,
      "zoneX": 0.0,
      "zoneY": 0.0,
      "zoneZ": 0.0,
      "zoneR": 0.0,
      "chapID": 1,
      "linkID": 0,
      "jijiDisp": 0,
      "wpnDisp": 1,
      "colFilterNear": 0,
      "colFilterFar": 0,
      "envSeam": 0,
      "evtLight": "",
      "hood": 1,
      "voice": 1,
      "cssnd": 1,
      "scriptName": "",
      "scriptStartId": 0,
      "toneMap": 0.0,
      "noRetarget": 0
    },
    {
      "$id": 19042,
      "evtName": "bf80301101",
      "mstxt": "blade/bf80301101",
      "setupID": 0,
      "chgStID": 0,
      "chgEdID": 0,
      "category": 4,
      "weather": 0,
      "clock": "",
      "clockStop": 0,
      "cloud": 0,
      "text": 1,
      "opFadeOutEnable": 1,
      "opFadeOut": 10,
      "opFadeWait": 0,
      "opFadeInEnable": 1,
      "opFadeIn": 15,
      "opFadeColR": 1,
      "opFadeColG": 1,
      "opFadeColB": 1,
      "edFadeOutEnable": 0,
      "edFadeOut": 0,
      "edFadeWait": 0,
      "edFadeInEnable": 0,
      "edFadeIn": 0,
      "edFadeColR": 0,
      "edFadeColG": 0,
      "edFadeColB": 0,
      "stFormID": 0,
      "edFormID": 0,
      "opBgm": 0,
      "edBgm": 0,
      "hideNpc": 0,
      "hideEne": 0,
      "hideMob": 0,
      "hideMap": 1,
      "outsiderOpt": 0,
      "outsiderEnable": 0,
      "outsiderType": 1,
      "outsiderX": 0.0,
      "outsiderY": 0.0,
      "outsiderZ": 0.0,
      "outsiderR": 0.0,
      "listenType": 0,
      "listenX": 0.0,
      "listenY": 0.0,
      "listenZ": 0.0,
      "nextID": 0,
      "zoneID": 46,
      "zoneX": 0.0,
      "zoneY": 0.0,
      "zoneZ": 0.0,
      "zoneR": 0.0,
      "chapID": 1,
      "linkID": 0,
      "jijiDisp": 0,
      "wpnDisp": 1,
      "colFilterNear": 0,
      "colFilterFar": 0,
      "envSeam": 0,
      "evtLight": "",
      "hood": 1,
      "voice": 1,
      "cssnd": 1,
      "scriptName": "",
      "scriptStartId": 0,
      "toneMap": 0.0,
      "noRetarget": 0
    },
    {
      "$id": 19043,
      "evtName": "bf80301201",
      "mstxt": "blade/bf80301201",
      "setupID": 0,
      "chgStID": 0,
      "chgEdID": 0,
      "category": 4,
      "weather": 0,
      "clock": "",
      "clockStop": 0,
      "cloud": 0,
      "text": 1,
      "opFadeOutEnable": 1,
      "opFadeOut": 10,
      "opFadeWait": 0,
      "opFadeInEnable": 1,
      "opFadeIn": 15,
      "opFadeColR": 1,
      "opFadeColG": 1,
      "opFadeColB": 1,
      "edFadeOutEnable": 0,
      "edFadeOut": 0,
      "edFadeWait": 0,
      "edFadeInEnable": 0,
      "edFadeIn": 0,
      "edFadeColR": 0,
      "edFadeColG": 0,
      "edFadeColB": 0,
      "stFormID": 0,
      "edFormID": 0,
      "opBgm": 0,
      "edBgm": 0,
      "hideNpc": 0,
      "hideEne": 0,
      "hideMob": 0,
      "hideMap": 1,
      "outsiderOpt": 0,
      "outsiderEnable": 0,
      "outsiderType": 1,
      "outsiderX": 0.0,
      "outsiderY": 0.0,
      "outsiderZ": 0.0,
      "outsiderR": 0.0,
      "listenType": 0,
      "listenX": 0.0,
      "listenY": 0.0,
      "listenZ": 0.0,
      "nextID": 0,
      "zoneID": 46,
      "zoneX": 0.0,
      "zoneY": 0.0,
      "zoneZ": 0.0,
      "zoneR": 0.0,
      "chapID": 1,
      "linkID": 0,
      "jijiDisp": 0,
      "wpnDisp": 1,
      "colFilterNear": 0,
      "colFilterFar": 0,
      "envSeam": 0,
      "evtLight": "",
      "hood": 1,
      "voice": 1,
      "cssnd": 1,
      "scriptName": "",
      "scriptStartId": 0,
      "toneMap": 0.0,
      "noRetarget": 0
    },
    {
      "$id": 19044,
      "evtName": "bf80301301",
      "mstxt": "blade/bf80301301",
      "setupID": 0,
      "chgStID": 0,
      "chgEdID": 0,
      "category": 4,
      "weather": 0,
      "clock": "",
      "clockStop": 0,
      "cloud": 0,
      "text": 1,
      "opFadeOutEnable": 1,
      "opFadeOut": 10,
      "opFadeWait": 0,
      "opFadeInEnable": 1,
      "opFadeIn": 15,
      "opFadeColR": 1,
      "opFadeColG": 1,
      "opFadeColB": 1,
      "edFadeOutEnable": 0,
      "edFadeOut": 0,
      "edFadeWait": 0,
      "edFadeInEnable": 0,
      "edFadeIn": 0,
      "edFadeColR": 0,
      "edFadeColG": 0,
      "edFadeColB": 0,
      "stFormID": 0,
      "edFormID": 0,
      "opBgm": 0,
      "edBgm": 0,
      "hideNpc": 0,
      "hideEne": 0,
      "hideMob": 0,
      "hideMap": 1,
      "outsiderOpt": 0,
      "outsiderEnable": 0,
      "outsiderType": 1,
      "outsiderX": 0.0,
      "outsiderY": 0.0,
      "outsiderZ": 0.0,
      "outsiderR": 0.0,
      "listenType": 0,
      "listenX": 0.0,
      "listenY": 0.0,
      "listenZ": 0.0,
      "nextID": 0,
      "zoneID": 46,
      "zoneX": 0.0,
      "zoneY": 0.0,
      "zoneZ": 0.0,
      "zoneR": 0.0,
      "chapID": 1,
      "linkID": 0,
      "jijiDisp": 0,
      "wpnDisp": 1,
      "colFilterNear": 0,
      "colFilterFar": 0,
      "envSeam": 0,
      "evtLight": "",
      "hood": 1,
      "voice": 1,
      "cssnd": 1,
      "scriptName": "",
      "scriptStartId": 0,
      "toneMap": 0.0,
      "noRetarget": 0
    },
    {
      "$id": 19045,
      "evtName": "bf80301401",
      "mstxt": "blade/bf80301401",
      "setupID": 0,
      "chgStID": 0,
      "chgEdID": 0,
      "category": 4,
      "weather": 0,
      "clock": "",
      "clockStop": 0,
      "cloud": 0,
      "text": 1,
      "opFadeOutEnable": 1,
      "opFadeOut": 10,
      "opFadeWait": 0,
      "opFadeInEnable": 1,
      "opFadeIn": 15,
      "opFadeColR": 1,
      "opFadeColG": 1,
      "opFadeColB": 1,
      "edFadeOutEnable": 0,
      "edFadeOut": 0,
      "edFadeWait": 0,
      "edFadeInEnable": 0,
      "edFadeIn": 0,
      "edFadeColR": 0,
      "edFadeColG": 0,
      "edFadeColB": 0,
      "stFormID": 0,
      "edFormID": 0,
      "opBgm": 0,
      "edBgm": 0,
      "hideNpc": 0,
      "hideEne": 0,
      "hideMob": 0,
      "hideMap": 1,
      "outsiderOpt": 0,
      "outsiderEnable": 0,
      "outsiderType": 1,
      "outsiderX": 0.0,
      "outsiderY": 0.0,
      "outsiderZ": 0.0,
      "outsiderR": 0.0,
      "listenType": 0,
      "listenX": 0.0,
      "listenY": 0.0,
      "listenZ": 0.0,
      "nextID": 0,
      "zoneID": 46,
      "zoneX": 0.0,
      "zoneY": 0.0,
      "zoneZ": 0.0,
      "zoneR": 0.0,
      "chapID": 1,
      "linkID": 0,
      "jijiDisp": 0,
      "wpnDisp": 1,
      "colFilterNear": 0,
      "colFilterFar": 0,
      "envSeam": 0,
      "evtLight": "",
      "hood": 1,
      "voice": 1,
      "cssnd": 1,
      "scriptName": "",
      "scriptStartId": 0,
      "toneMap": 0.0,
      "noRetarget": 0
    },
    {
      "$id": 19046,
      "evtName": "bf80301501",
      "mstxt": "blade/bf80301501",
      "setupID": 0,
      "chgStID": 0,
      "chgEdID": 0,
      "category": 4,
      "weather": 0,
      "clock": "",
      "clockStop": 0,
      "cloud": 0,
      "text": 1,
      "opFadeOutEnable": 1,
      "opFadeOut": 10,
      "opFadeWait": 0,
      "opFadeInEnable": 1,
      "opFadeIn": 15,
      "opFadeColR": 1,
      "opFadeColG": 1,
      "opFadeColB": 1,
      "edFadeOutEnable": 0,
      "edFadeOut": 0,
      "edFadeWait": 0,
      "edFadeInEnable": 0,
      "edFadeIn": 0,
      "edFadeColR": 0,
      "edFadeColG": 0,
      "edFadeColB": 0,
      "stFormID": 0,
      "edFormID": 0,
      "opBgm": 0,
      "edBgm": 0,
      "hideNpc": 0,
      "hideEne": 0,
      "hideMob": 0,
      "hideMap": 1,
      "outsiderOpt": 0,
      "outsiderEnable": 0,
      "outsiderType": 1,
      "outsiderX": 0.0,
      "outsiderY": 0.0,
      "outsiderZ": 0.0,
      "outsiderR": 0.0,
      "listenType": 0,
      "listenX": 0.0,
      "listenY": 0.0,
      "listenZ": 0.0,
      "nextID": 0,
      "zoneID": 46,
      "zoneX": 0.0,
      "zoneY": 0.0,
      "zoneZ": 0.0,
      "zoneR": 0.0,
      "chapID": 1,
      "linkID": 0,
      "jijiDisp": 0,
      "wpnDisp": 1,
      "colFilterNear": 0,
      "colFilterFar": 0,
      "envSeam": 0,
      "evtLight": "",
      "hood": 1,
      "voice": 1,
      "cssnd": 1,
      "scriptName": "",
      "scriptStartId": 0,
      "toneMap": 0.0,
      "noRetarget": 0
    },
    {
      "$id": 19047,
      "evtName": "bf80301601",
      "mstxt": "blade/bf80301601",
      "setupID": 0,
      "chgStID": 0,
      "chgEdID": 0,
      "category": 4,
      "weather": 0,
      "clock": "",
      "clockStop": 0,
      "cloud": 0,
      "text": 1,
      "opFadeOutEnable": 1,
      "opFadeOut": 10,
      "opFadeWait": 0,
      "opFadeInEnable": 1,
      "opFadeIn": 15,
      "opFadeColR": 1,
      "opFadeColG": 1,
      "opFadeColB": 1,
      "edFadeOutEnable": 0,
      "edFadeOut": 0,
      "edFadeWait": 0,
      "edFadeInEnable": 0,
      "edFadeIn": 0,
      "edFadeColR": 0,
      "edFadeColG": 0,
      "edFadeColB": 0,
      "stFormID": 0,
      "edFormID": 0,
      "opBgm": 0,
      "edBgm": 0,
      "hideNpc": 0,
      "hideEne": 0,
      "hideMob": 0,
      "hideMap": 1,
      "outsiderOpt": 0,
      "outsiderEnable": 0,
      "outsiderType": 1,
      "outsiderX": 0.0,
      "outsiderY": 0.0,
      "outsiderZ": 0.0,
      "outsiderR": 0.0,
      "listenType": 0,
      "listenX": 0.0,
      "listenY": 0.0,
      "listenZ": 0.0,
      "nextID": 0,
      "zoneID": 46,
      "zoneX": 0.0,
      "zoneY": 0.0,
      "zoneZ": 0.0,
      "zoneR": 0.0,
      "chapID": 1,
      "linkID": 0,
      "jijiDisp": 0,
      "wpnDisp": 1,
      "colFilterNear": 0,
      "colFilterFar": 0,
      "envSeam": 0,
      "evtLight": "",
      "hood": 1,
      "voice": 1,
      "cssnd": 1,
      "scriptName": "",
      "scriptStartId": 0,
      "toneMap": 0.0,
      "noRetarget": 0
    },
    {
      "$id": 19048,
      "evtName": "bf80301701",
      "mstxt": "blade/bf80301701",
      "setupID": 0,
      "chgStID": 0,
      "chgEdID": 0,
      "category": 4,
      "weather": 0,
      "clock": "",
      "clockStop": 0,
      "cloud": 0,
      "text": 1,
      "opFadeOutEnable": 1,
      "opFadeOut": 10,
      "opFadeWait": 0,
      "opFadeInEnable": 1,
      "opFadeIn": 15,
      "opFadeColR": 1,
      "opFadeColG": 1,
      "opFadeColB": 1,
      "edFadeOutEnable": 0,
      "edFadeOut": 0,
      "edFadeWait": 0,
      "edFadeInEnable": 0,
      "edFadeIn": 0,
      "edFadeColR": 0,
      "edFadeColG": 0,
      "edFadeColB": 0,
      "stFormID": 0,
      "edFormID": 0,
      "opBgm": 0,
      "edBgm": 0,
      "hideNpc": 0,
      "hideEne": 0,
      "hideMob": 0,
      "hideMap": 1,
      "outsiderOpt": 0,
      "outsiderEnable": 0,
      "outsiderType": 1,
      "outsiderX": 0.0,
      "outsiderY": 0.0,
      "outsiderZ": 0.0,
      "outsiderR": 0.0,
      "listenType": 0,
      "listenX": 0.0,
      "listenY": 0.0,
      "listenZ": 0.0,
      "nextID": 0,
      "zoneID": 46,
      "zoneX": 0.0,
      "zoneY": 0.0,
      "zoneZ": 0.0,
      "zoneR": 0.0,
      "chapID": 1,
      "linkID": 0,
      "jijiDisp": 0,
      "wpnDisp": 1,
      "colFilterNear": 0,
      "colFilterFar": 0,
      "envSeam": 0,
      "evtLight": "",
      "hood": 1,
      "voice": 1,
      "cssnd": 1,
      "scriptName": "",
      "scriptStartId": 0,
      "toneMap": 0.0,
      "noRetarget": 0
    },
    {
      "$id": 19049,
      "evtName": "bf80301801",
      "mstxt": "blade/bf80301801",
      "setupID": 0,
      "chgStID": 0,
      "chgEdID": 0,
      "category": 4,
      "weather": 0,
      "clock": "",
      "clockStop": 0,
      "cloud": 0,
      "text": 1,
      "opFadeOutEnable": 1,
      "opFadeOut": 10,
      "opFadeWait": 0,
      "opFadeInEnable": 1,
      "opFadeIn": 15,
      "opFadeColR": 1,
      "opFadeColG": 1,
      "opFadeColB": 1,
      "edFadeOutEnable": 0,
      "edFadeOut": 0,
      "edFadeWait": 0,
      "edFadeInEnable": 0,
      "edFadeIn": 0,
      "edFadeColR": 0,
      "edFadeColG": 0,
      "edFadeColB": 0,
      "stFormID": 0,
      "edFormID": 0,
      "opBgm": 0,
      "edBgm": 0,
      "hideNpc": 0,
      "hideEne": 0,
      "hideMob": 0,
      "hideMap": 1,
      "outsiderOpt": 0,
      "outsiderEnable": 0,
      "outsiderType": 1,
      "outsiderX": 0.0,
      "outsiderY": 0.0,
      "outsiderZ": 0.0,
      "outsiderR": 0.0,
      "listenType": 0,
      "listenX": 0.0,
      "listenY": 0.0,
      "listenZ": 0.0,
      "nextID": 0,
      "zoneID": 46,
      "zoneX": 0.0,
      "zoneY": 0.0,
      "zoneZ": 0.0,
      "zoneR": 0.0,
      "chapID": 1,
      "linkID": 0,
      "jijiDisp": 0,
      "wpnDisp": 1,
      "colFilterNear": 0,
      "colFilterFar": 0,
      "envSeam": 0,
      "evtLight": "",
      "hood": 1,
      "voice": 1,
      "cssnd": 1,
      "scriptName": "",
      "scriptStartId": 0,
      "toneMap": 0.0,
      "noRetarget": 0
    },
    {
      "$id": 19050,
      "evtName": "bf80301901",
      "mstxt": "blade/bf80301901",
      "setupID": 0,
      "chgStID": 0,
      "chgEdID": 0,
      "category": 4,
      "weather": 0,
      "clock": "",
      "clockStop": 0,
      "cloud": 0,
      "text": 1,
      "opFadeOutEnable": 1,
      "opFadeOut": 10,
      "opFadeWait": 0,
      "opFadeInEnable": 1,
      "opFadeIn": 15,
      "opFadeColR": 1,
      "opFadeColG": 1,
      "opFadeColB": 1,
      "edFadeOutEnable": 0,
      "edFadeOut": 0,
      "edFadeWait": 0,
      "edFadeInEnable": 0,
      "edFadeIn": 0,
      "edFadeColR": 0,
      "edFadeColG": 0,
      "edFadeColB": 0,
      "stFormID": 0,
      "edFormID": 0,
      "opBgm": 0,
      "edBgm": 0,
      "hideNpc": 0,
      "hideEne": 0,
      "hideMob": 0,
      "hideMap": 1,
      "outsiderOpt": 0,
      "outsiderEnable": 0,
      "outsiderType": 1,
      "outsiderX": 0.0,
      "outsiderY": 0.0,
      "outsiderZ": 0.0,
      "outsiderR": 0.0,
      "listenType": 0,
      "listenX": 0.0,
      "listenY": 0.0,
      "listenZ": 0.0,
      "nextID": 0,
      "zoneID": 46,
      "zoneX": 0.0,
      "zoneY": 0.0,
      "zoneZ": 0.0,
      "zoneR": 0.0,
      "chapID": 1,
      "linkID": 0,
      "jijiDisp": 0,
      "wpnDisp": 1,
      "colFilterNear": 0,
      "colFilterFar": 0,
      "envSeam": 0,
      "evtLight": "",
      "hood": 1,
      "voice": 1,
      "cssnd": 1,
      "scriptName": "",
      "scriptStartId": 0,
      "toneMap": 0.0,
      "noRetarget": 0
    },
    {
      "$id": 19051,
      "evtName": "bf80302001",
      "mstxt": "blade/bf80302001",
      "setupID": 0,
      "chgStID": 0,
      "chgEdID": 0,
      "category": 4,
      "weather": 0,
      "clock": "",
      "clockStop": 0,
      "cloud": 0,
      "text": 1,
      "opFadeOutEnable": 1,
      "opFadeOut": 10,
      "opFadeWait": 0,
      "opFadeInEnable": 1,
      "opFadeIn": 15,
      "opFadeColR": 1,
      "opFadeColG": 1,
      "opFadeColB": 1,
      "edFadeOutEnable": 0,
      "edFadeOut": 0,
      "edFadeWait": 0,
      "edFadeInEnable": 0,
      "edFadeIn": 0,
      "edFadeColR": 0,
      "edFadeColG": 0,
      "edFadeColB": 0,
      "stFormID": 0,
      "edFormID": 0,
      "opBgm": 0,
      "edBgm": 0,
      "hideNpc": 0,
      "hideEne": 0,
      "hideMob": 0,
      "hideMap": 1,
      "outsiderOpt": 0,
      "outsiderEnable": 0,
      "outsiderType": 1,
      "outsiderX": 0.0,
      "outsiderY": 0.0,
      "outsiderZ": 0.0,
      "outsiderR": 0.0,
      "listenType": 0,
      "listenX": 0.0,
      "listenY": 0.0,
      "listenZ": 0.0,
      "nextID": 0,
      "zoneID": 46,
      "zoneX": 0.0,
      "zoneY": 0.0,
      "zoneZ": 0.0,
      "zoneR": 0.0,
      "chapID": 1,
      "linkID": 0,
      "jijiDisp": 0,
      "wpnDisp": 1,
      "colFilterNear": 0,
      "colFilterFar": 0,
      "envSeam": 0,
      "evtLight": "",
      "hood": 1,
      "voice": 1,
      "cssnd": 1,
      "scriptName": "",
      "scriptStartId": 0,
      "toneMap": 0.0,
      "noRetarget": 0
    },
    {
      "$id": 19052,
      "evtName": "bf80302101",
      "mstxt": "blade/bf80302101",
      "setupID": 0,
      "chgStID": 0,
      "chgEdID": 0,
      "category": 4,
      "weather": 0,
      "clock": "",
      "clockStop": 0,
      "cloud": 0,
      "text": 1,
      "opFadeOutEnable": 1,
      "opFadeOut": 10,
      "opFadeWait": 0,
      "opFadeInEnable": 1,
      "opFadeIn": 15,
      "opFadeColR": 1,
      "opFadeColG": 1,
      "opFadeColB": 1,
      "edFadeOutEnable": 0,
      "edFadeOut": 0,
      "edFadeWait": 0,
      "edFadeInEnable": 0,
      "edFadeIn": 0,
      "edFadeColR": 0,
      "edFadeColG": 0,
      "edFadeColB": 0,
      "stFormID": 0,
      "edFormID": 0,
      "opBgm": 0,
      "edBgm": 0,
      "hideNpc": 0,
      "hideEne": 0,
      "hideMob": 0,
      "hideMap": 1,
      "outsiderOpt": 0,
      "outsiderEnable": 0,
      "outsiderType": 1,
      "outsiderX": 0.0,
      "outsiderY": 0.0,
      "outsiderZ": 0.0,
      "outsiderR": 0.0,
      "listenType": 0,
      "listenX": 0.0,
      "listenY": 0.0,
      "listenZ": 0.0,
      "nextID": 0,
      "zoneID": 46,
      "zoneX": 0.0,
      "zoneY": 0.0,
      "zoneZ": 0.0,
      "zoneR": 0.0,
      "chapID": 1,
      "linkID": 0,
      "jijiDisp": 0,
      "wpnDisp": 1,
      "colFilterNear": 0,
      "colFilterFar": 0,
      "envSeam": 0,
      "evtLight": "",
      "hood": 1,
      "voice": 1,
      "cssnd": 1,
      "scriptName": "",
      "scriptStartId": 0,
      "toneMap": 0.0,
      "noRetarget": 0
    },
    {
      "$id": 19053,
      "evtName": "bf80302201",
      "mstxt": "blade/bf80302201",
      "setupID": 0,
      "chgStID": 0,
      "chgEdID": 0,
      "category": 4,
      "weather": 0,
      "clock": "",
      "clockStop": 0,
      "cloud": 0,
      "text": 1,
      "opFadeOutEnable": 1,
      "opFadeOut": 10,
      "opFadeWait": 0,
      "opFadeInEnable": 1,
      "opFadeIn": 15,
      "opFadeColR": 1,
      "opFadeColG": 1,
      "opFadeColB": 1,
      "edFadeOutEnable": 0,
      "edFadeOut": 0,
      "edFadeWait": 0,
      "edFadeInEnable": 0,
      "edFadeIn": 0,
      "edFadeColR": 0,
      "edFadeColG": 0,
      "edFadeColB": 0,
      "stFormID": 0,
      "edFormID": 0,
      "opBgm": 0,
      "edBgm": 0,
      "hideNpc": 0,
      "hideEne": 0,
      "hideMob": 0,
      "hideMap": 1,
      "outsiderOpt": 0,
      "outsiderEnable": 0,
      "outsiderType": 1,
      "outsiderX": 0.0,
      "outsiderY": 0.0,
      "outsiderZ": 0.0,
      "outsiderR": 0.0,
      "listenType": 0,
      "listenX": 0.0,
      "listenY": 0.0,
      "listenZ": 0.0,
      "nextID": 0,
      "zoneID": 46,
      "zoneX": 0.0,
      "zoneY": 0.0,
      "zoneZ": 0.0,
      "zoneR": 0.0,
      "chapID": 1,
      "linkID": 0,
      "jijiDisp": 0,
      "wpnDisp": 1,
      "colFilterNear": 0,
      "colFilterFar": 0,
      "envSeam": 0,
      "evtLight": "",
      "hood": 1,
      "voice": 1,
      "cssnd": 1,
      "scriptName": "",
      "scriptStartId": 0,
      "toneMap": 0.0,
      "noRetarget": 0
    },
    {
      "$id": 19054,
      "evtName": "bf80302301",
      "mstxt": "blade/bf80302301",
      "setupID": 0,
      "chgStID": 0,
      "chgEdID": 0,
      "category": 4,
      "weather": 0,
      "clock": "",
      "clockStop": 0,
      "cloud": 0,
      "text": 1,
      "opFadeOutEnable": 1,
      "opFadeOut": 10,
      "opFadeWait": 0,
      "opFadeInEnable": 1,
      "opFadeIn": 15,
      "opFadeColR": 1,
      "opFadeColG": 1,
      "opFadeColB": 1,
      "edFadeOutEnable": 0,
      "edFadeOut": 0,
      "edFadeWait": 0,
      "edFadeInEnable": 0,
      "edFadeIn": 0,
      "edFadeColR": 0,
      "edFadeColG": 0,
      "edFadeColB": 0,
      "stFormID": 0,
      "edFormID": 0,
      "opBgm": 0,
      "edBgm": 0,
      "hideNpc": 0,
      "hideEne": 0,
      "hideMob": 0,
      "hideMap": 1,
      "outsiderOpt": 0,
      "outsiderEnable": 0,
      "outsiderType": 1,
      "outsiderX": 0.0,
      "outsiderY": 0.0,
      "outsiderZ": 0.0,
      "outsiderR": 0.0,
      "listenType": 0,
      "listenX": 0.0,
      "listenY": 0.0,
      "listenZ": 0.0,
      "nextID": 0,
      "zoneID": 46,
      "zoneX": 0.0,
      "zoneY": 0.0,
      "zoneZ": 0.0,
      "zoneR": 0.0,
      "chapID": 1,
      "linkID": 0,
      "jijiDisp": 0,
      "wpnDisp": 1,
      "colFilterNear": 0,
      "colFilterFar": 0,
      "envSeam": 0,
      "evtLight": "",
      "hood": 1,
      "voice": 1,
      "cssnd": 1,
      "scriptName": "",
      "scriptStartId": 0,
      "toneMap": 0.0,
      "noRetarget": 0
    },
    {
      "$id": 19055,
      "evtName": "bf80302401",
      "mstxt": "blade/bf80302401",
      "setupID": 0,
      "chgStID": 0,
      "chgEdID": 0,
      "category": 4,
      "weather": 0,
      "clock": "",
      "clockStop": 0,
      "cloud": 0,
      "text": 1,
      "opFadeOutEnable": 1,
      "opFadeOut": 10,
      "opFadeWait": 0,
      "opFadeInEnable": 1,
      "opFadeIn": 15,
      "opFadeColR": 1,
      "opFadeColG": 1,
      "opFadeColB": 1,
      "edFadeOutEnable": 0,
      "edFadeOut": 0,
      "edFadeWait": 0,
      "edFadeInEnable": 0,
      "edFadeIn": 0,
      "edFadeColR": 0,
      "edFadeColG": 0,
      "edFadeColB": 0,
      "stFormID": 0,
      "edFormID": 0,
      "opBgm": 0,
      "edBgm": 0,
      "hideNpc": 0,
      "hideEne": 0,
      "hideMob": 0,
      "hideMap": 1,
      "outsiderOpt": 0,
      "outsiderEnable": 0,
      "outsiderType": 1,
      "outsiderX": 0.0,
      "outsiderY": 0.0,
      "outsiderZ": 0.0,
      "outsiderR": 0.0,
      "listenType": 0,
      "listenX": 0.0,
      "listenY": 0.0,
      "listenZ": 0.0,
      "nextID": 0,
      "zoneID": 46,
      "zoneX": 0.0,
      "zoneY": 0.0,
      "zoneZ": 0.0,
      "zoneR": 0.0,
      "chapID": 1,
      "linkID": 0,
      "jijiDisp": 0,
      "wpnDisp": 1,
      "colFilterNear": 0,
      "colFilterFar": 0,
      "envSeam": 0,
      "evtLight": "",
      "hood": 1,
      "voice": 1,
      "cssnd": 1,
      "scriptName": "",
      "scriptStartId": 0,
      "toneMap": 0.0,
      "noRetarget": 0
    },
    {
      "$id": 19056,
      "evtName": "bf80302501",
      "mstxt": "blade/bf80302501",
      "setupID": 0,
      "chgStID": 0,
      "chgEdID": 0,
      "category": 4,
      "weather": 0,
      "clock": "",
      "clockStop": 0,
      "cloud": 0,
      "text": 1,
      "opFadeOutEnable": 1,
      "opFadeOut": 10,
      "opFadeWait": 0,
      "opFadeInEnable": 1,
      "opFadeIn": 15,
      "opFadeColR": 1,
      "opFadeColG": 1,
      "opFadeColB": 1,
      "edFadeOutEnable": 0,
      "edFadeOut": 0,
      "edFadeWait": 0,
      "edFadeInEnable": 0,
      "edFadeIn": 0,
      "edFadeColR": 0,
      "edFadeColG": 0,
      "edFadeColB": 0,
      "stFormID": 0,
      "edFormID": 0,
      "opBgm": 0,
      "edBgm": 0,
      "hideNpc": 0,
      "hideEne": 0,
      "hideMob": 0,
      "hideMap": 1,
      "outsiderOpt": 0,
      "outsiderEnable": 0,
      "outsiderType": 1,
      "outsiderX": 0.0,
      "outsiderY": 0.0,
      "outsiderZ": 0.0,
      "outsiderR": 0.0,
      "listenType": 0,
      "listenX": 0.0,
      "listenY": 0.0,
      "listenZ": 0.0,
      "nextID": 0,
      "zoneID": 46,
      "zoneX": 0.0,
      "zoneY": 0.0,
      "zoneZ": 0.0,
      "zoneR": 0.0,
      "chapID": 1,
      "linkID": 0,
      "jijiDisp": 0,
      "wpnDisp": 1,
      "colFilterNear": 0,
      "colFilterFar": 0,
      "envSeam": 0,
      "evtLight": "",
      "hood": 1,
      "voice": 1,
      "cssnd": 1,
      "scriptName": "",
      "scriptStartId": 0,
      "toneMap": 0.0,
      "noRetarget": 0
    },
    {
      "$id": 19057,
      "evtName": "bf80302601",
      "mstxt": "blade/bf80302601",
      "setupID": 0,
      "chgStID": 0,
      "chgEdID": 0,
      "category": 4,
      "weather": 0,
      "clock": "",
      "clockStop": 0,
      "cloud": 0,
      "text": 1,
      "opFadeOutEnable": 1,
      "opFadeOut": 10,
      "opFadeWait": 0,
      "opFadeInEnable": 1,
      "opFadeIn": 15,
      "opFadeColR": 1,
      "opFadeColG": 1,
      "opFadeColB": 1,
      "edFadeOutEnable": 0,
      "edFadeOut": 0,
      "edFadeWait": 0,
      "edFadeInEnable": 0,
      "edFadeIn": 0,
      "edFadeColR": 0,
      "edFadeColG": 0,
      "edFadeColB": 0,
      "stFormID": 0,
      "edFormID": 0,
      "opBgm": 0,
      "edBgm": 0,
      "hideNpc": 0,
      "hideEne": 0,
      "hideMob": 0,
      "hideMap": 1,
      "outsiderOpt": 0,
      "outsiderEnable": 0,
      "outsiderType": 1,
      "outsiderX": 0.0,
      "outsiderY": 0.0,
      "outsiderZ": 0.0,
      "outsiderR": 0.0,
      "listenType": 0,
      "listenX": 0.0,
      "listenY": 0.0,
      "listenZ": 0.0,
      "nextID": 0,
      "zoneID": 46,
      "zoneX": 0.0,
      "zoneY": 0.0,
      "zoneZ": 0.0,
      "zoneR": 0.0,
      "chapID": 1,
      "linkID": 0,
      "jijiDisp": 0,
      "wpnDisp": 1,
      "colFilterNear": 0,
      "colFilterFar": 0,
      "envSeam": 0,
      "evtLight": "",
      "hood": 1,
      "voice": 1,
      "cssnd": 1,
      "scriptName": "",
      "scriptStartId": 0,
      "toneMap": 0.0,
      "noRetarget": 0
    },
    {
      "$id": 19058,
      "evtName": "bf80302701",
      "mstxt": "blade/bf80302701",
      "setupID": 0,
      "chgStID": 0,
      "chgEdID": 0,
      "category": 4,
      "weather": 0,
      "clock": "",
      "clockStop": 0,
      "cloud": 0,
      "text": 1,
      "opFadeOutEnable": 1,
      "opFadeOut": 10,
      "opFadeWait": 0,
      "opFadeInEnable": 1,
      "opFadeIn": 15,
      "opFadeColR": 1,
      "opFadeColG": 1,
      "opFadeColB": 1,
      "edFadeOutEnable": 0,
      "edFadeOut": 0,
      "edFadeWait": 0,
      "edFadeInEnable": 0,
      "edFadeIn": 0,
      "edFadeColR": 0,
      "edFadeColG": 0,
      "edFadeColB": 0,
      "stFormID": 0,
      "edFormID": 0,
      "opBgm": 0,
      "edBgm": 0,
      "hideNpc": 0,
      "hideEne": 0,
      "hideMob": 0,
      "hideMap": 1,
      "outsiderOpt": 0,
      "outsiderEnable": 0,
      "outsiderType": 1,
      "outsiderX": 0.0,
      "outsiderY": 0.0,
      "outsiderZ": 0.0,
      "outsiderR": 0.0,
      "listenType": 0,
      "listenX": 0.0,
      "listenY": 0.0,
      "listenZ": 0.0,
      "nextID": 0,
      "zoneID": 46,
      "zoneX": 0.0,
      "zoneY": 0.0,
      "zoneZ": 0.0,
      "zoneR": 0.0,
      "chapID": 1,
      "linkID": 0,
      "jijiDisp": 0,
      "wpnDisp": 1,
      "colFilterNear": 0,
      "colFilterFar": 0,
      "envSeam": 0,
      "evtLight": "",
      "hood": 1,
      "voice": 1,
      "cssnd": 1,
      "scriptName": "",
      "scriptStartId": 0,
      "toneMap": 0.0,
      "noRetarget": 0
    },
    {
      "$id": 19059,
      "evtName": "bf80303101",
      "mstxt": "blade/bf80303101",
      "setupID": 0,
      "chgStID": 0,
      "chgEdID": 0,
      "category": 4,
      "weather": 0,
      "clock": "",
      "clockStop": 0,
      "cloud": 0,
      "text": 1,
      "opFadeOutEnable": 1,
      "opFadeOut": 10,
      "opFadeWait": 0,
      "opFadeInEnable": 1,
      "opFadeIn": 15,
      "opFadeColR": 1,
      "opFadeColG": 1,
      "opFadeColB": 1,
      "edFadeOutEnable": 0,
      "edFadeOut": 0,
      "edFadeWait": 0,
      "edFadeInEnable": 0,
      "edFadeIn": 0,
      "edFadeColR": 0,
      "edFadeColG": 0,
      "edFadeColB": 0,
      "stFormID": 0,
      "edFormID": 0,
      "opBgm": 0,
      "edBgm": 0,
      "hideNpc": 0,
      "hideEne": 0,
      "hideMob": 0,
      "hideMap": 1,
      "outsiderOpt": 0,
      "outsiderEnable": 0,
      "outsiderType": 1,
      "outsiderX": 0.0,
      "outsiderY": 0.0,
      "outsiderZ": 0.0,
      "outsiderR": 0.0,
      "listenType": 0,
      "listenX": 0.0,
      "listenY": 0.0,
      "listenZ": 0.0,
      "nextID": 0,
      "zoneID": 46,
      "zoneX": 0.0,
      "zoneY": 0.0,
      "zoneZ": 0.0,
      "zoneR": 0.0,
      "chapID": 1,
      "linkID": 0,
      "jijiDisp": 0,
      "wpnDisp": 1,
      "colFilterNear": 0,
      "colFilterFar": 0,
      "envSeam": 0,
      "evtLight": "",
      "hood": 1,
      "voice": 1,
      "cssnd": 1,
      "scriptName": "",
      "scriptStartId": 0,
      "toneMap": 0.0,
      "noRetarget": 0
    },
    {
      "$id": 19060,
      "evtName": "bf80400201",
      "mstxt": "blade/bf80400201",
      "setupID": 0,
      "chgStID": 0,
      "chgEdID": 0,
      "category": 4,
      "weather": 0,
      "clock": "",
      "clockStop": 0,
      "cloud": 0,
      "text": 1,
      "opFadeOutEnable": 1,
      "opFadeOut": 10,
      "opFadeWait": 0,
      "opFadeInEnable": 1,
      "opFadeIn": 15,
      "opFadeColR": 1,
      "opFadeColG": 1,
      "opFadeColB": 1,
      "edFadeOutEnable": 0,
      "edFadeOut": 0,
      "edFadeWait": 0,
      "edFadeInEnable": 0,
      "edFadeIn": 0,
      "edFadeColR": 0,
      "edFadeColG": 0,
      "edFadeColB": 0,
      "stFormID": 0,
      "edFormID": 0,
      "opBgm": 0,
      "edBgm": 0,
      "hideNpc": 0,
      "hideEne": 0,
      "hideMob": 0,
      "hideMap": 1,
      "outsiderOpt": 0,
      "outsiderEnable": 0,
      "outsiderType": 1,
      "outsiderX": 0.0,
      "outsiderY": 0.0,
      "outsiderZ": 0.0,
      "outsiderR": 0.0,
      "listenType": 0,
      "listenX": 0.0,
      "listenY": 0.0,
      "listenZ": 0.0,
      "nextID": 0,
      "zoneID": 46,
      "zoneX": 0.0,
      "zoneY": 0.0,
      "zoneZ": 0.0,
      "zoneR": 0.0,
      "chapID": 1,
      "linkID": 0,
      "jijiDisp": 0,
      "wpnDisp": 1,
      "colFilterNear": 0,
      "colFilterFar": 0,
      "envSeam": 0,
      "evtLight": "",
      "hood": 1,
      "voice": 1,
      "cssnd": 1,
      "scriptName": "",
      "scriptStartId": 0,
      "toneMap": 0.0,
      "noRetarget": 0
    },
    {
      "$id": 19061,
      "evtName": "bf80400301",
      "mstxt": "blade/bf80400301",
      "setupID": 0,
      "chgStID": 0,
      "chgEdID": 0,
      "category": 4,
      "weather": 0,
      "clock": "",
      "clockStop": 0,
      "cloud": 0,
      "text": 1,
      "opFadeOutEnable": 1,
      "opFadeOut": 10,
      "opFadeWait": 0,
      "opFadeInEnable": 1,
      "opFadeIn": 15,
      "opFadeColR": 1,
      "opFadeColG": 1,
      "opFadeColB": 1,
      "edFadeOutEnable": 0,
      "edFadeOut": 0,
      "edFadeWait": 0,
      "edFadeInEnable": 0,
      "edFadeIn": 0,
      "edFadeColR": 0,
      "edFadeColG": 0,
      "edFadeColB": 0,
      "stFormID": 0,
      "edFormID": 0,
      "opBgm": 0,
      "edBgm": 0,
      "hideNpc": 0,
      "hideEne": 0,
      "hideMob": 0,
      "hideMap": 1,
      "outsiderOpt": 0,
      "outsiderEnable": 0,
      "outsiderType": 1,
      "outsiderX": 0.0,
      "outsiderY": 0.0,
      "outsiderZ": 0.0,
      "outsiderR": 0.0,
      "listenType": 0,
      "listenX": 0.0,
      "listenY": 0.0,
      "listenZ": 0.0,
      "nextID": 0,
      "zoneID": 46,
      "zoneX": 0.0,
      "zoneY": 0.0,
      "zoneZ": 0.0,
      "zoneR": 0.0,
      "chapID": 1,
      "linkID": 0,
      "jijiDisp": 0,
      "wpnDisp": 1,
      "colFilterNear": 0,
      "colFilterFar": 0,
      "envSeam": 0,
      "evtLight": "",
      "hood": 1,
      "voice": 1,
      "cssnd": 1,
      "scriptName": "",
      "scriptStartId": 0,
      "toneMap": 0.0,
      "noRetarget": 0
    }
  ]
}