{
  "schema": [
    {
      "name": "obj_name",
      "type": 7
    },
    {
      "name": "text_id",
      "type": 3
    }
  ],
  "rows": [
    {
      "$id": 1,
      "obj_name": "TXT_dr_name",
      "text_id": 178
    },
    {
      "$id": 2,
      "obj_name": "TXT_current_title",
      "text_id": 183
    },
    {
      "$id": 3,
      "obj_name": "TXT_reserve_title",
      "text_id": 184
    },
    {
      "$id": 4,
      "obj_name": "TXT_title",
      "text_id": 179
    },
    {
      "$id": 5,
      "obj_name": "TXT_hp_title",
      "text_id": 187
    },
    {
      "$id": 6,
      "obj_name": "TXT_hp_num",
      "text_id": 185
    },
    {
      "$id": 7,
      "obj_name": "TXT_hp_max",
      "text_id": 185
    },
    {
      "$id": 8,
      "obj_name": "TXT_hp_slash",
      "text_id": 189
    },
    {
      "$id": 9,
      "obj_name": "TXT_lv_title",
      "text_id": 188
    },
    {
      "$id": 10,
      "obj_name": "TXT_lv_num",
      "text_id": 190
    },
    {
      "$id": 11,
      "obj_name": "TXT_dr_detail_title",
      "text_id": 193
    },
    {
      "$id": 12,
      "obj_name": "TXT_dr_detail_name",
      "text_id": 192
    },
    {
      "$id": 13,
      "obj_name": "TXT_dr_detail_lv_title",
      "text_id": 213
    },
    {
      "$id": 14,
      "obj_name": "TXT_dr_detail_lv_num",
      "text_id": 214
    },
    {
      "$id": 15,
      "obj_name": "TXT_dr_detail_hp_title",
      "text_id": 212
    },
    {
      "$id": 16,
      "obj_name": "TXT_dr_detail_hp_num",
      "text_id": 211
    },
    {
      "$id": 17,
      "obj_name": "TXT_dr_detail_hp_max",
      "text_id": 211
    },
    {
      "$id": 18,
      "obj_name": "TXT_dr_detail_hp_slash",
      "text_id": 215
    },
    {
      "$id": 19,
      "obj_name": "TXT_st_atk_title",
      "text_id": 194
    },
    {
      "$id": 20,
      "obj_name": "TXT_st_atk_damage",
      "text_id": 198
    },
    {
      "$id": 21,
      "obj_name": "TXT_st_atk_damage_num",
      "text_id": 208
    },
    {
      "$id": 22,
      "obj_name": "TXT_st_def_title",
      "text_id": 195
    },
    {
      "$id": 23,
      "obj_name": "TXT_st_def_phys",
      "text_id": 191
    },
    {
      "$id": 24,
      "obj_name": "TXT_st_def_phys_num",
      "text_id": 208
    },
    {
      "$id": 25,
      "obj_name": "TXT_st_def_ether",
      "text_id": 200
    },
    {
      "$id": 26,
      "obj_name": "TXT_st_def_ether_num",
      "text_id": 208
    },
    {
      "$id": 27,
      "obj_name": "TXT_st_prob_title",
      "text_id": 196
    },
    {
      "$id": 28,
      "obj_name": "TXT_st_prob_critical",
      "text_id": 201
    },
    {
      "$id": 29,
      "obj_name": "TXT_st_prob_critical_num",
      "text_id": 209
    },
    {
      "$id": 30,
      "obj_name": "TXT_st_prob_guard",
      "text_id": 202
    },
    {
      "$id": 31,
      "obj_name": "TXT_st_prob_guard_num",
      "text_id": 209
    },
    {
      "$id": 32,
      "obj_name": "TXT_st_base_title",
      "text_id": 197
    },
    {
      "$id": 33,
      "obj_name": "TXT_st_base_strength",
      "text_id": 203
    },
    {
      "$id": 34,
      "obj_name": "TXT_st_base_strength_num",
      "text_id": 208
    },
    {
      "$id": 35,
      "obj_name": "TXT_st_base_ether",
      "text_id": 204
    },
    {
      "$id": 36,
      "obj_name": "TXT_st_base_ether_num",
      "text_id": 208
    },
    {
      "$id": 37,
      "obj_name": "TXT_st_base_dex",
      "text_id": 205
    },
    {
      "$id": 38,
      "obj_name": "TXT_st_base_dex_num",
      "text_id": 208
    },
    {
      "$id": 39,
      "obj_name": "TXT_st_base_agility",
      "text_id": 206
    },
    {
      "$id": 40,
      "obj_name": "TXT_st_base_agility_num",
      "text_id": 208
    },
    {
      "$id": 41,
      "obj_name": "TXT_st_base_luck",
      "text_id": 207
    },
    {
      "$id": 42,
      "obj_name": "TXT_st_base_luck_num",
      "text_id": 208
    },
    {
      "$id": 43,
      "obj_name": "TXT_arts_info_title",
      "text_id": 224
    },
    {
      "$id": 44,
      "obj_name": "TXT_blade_role",
      "text_id": 217
    },
    {
      "$id": 45,
      "obj_name": "TXT_blade_set_name01",
      "text_id": 13
    },
    {
      "$id": 46,
      "obj_name": "TXT_blade_set_name02",
      "text_id": 13
    },
    {
      "$id": 47,
      "obj_name": "TXT_blade_set_name03",
      "text_id": 13
    },
    {
      "$id": 48,
      "obj_name": "TXT_blade_role_set_name",
      "text_id": 223
    },
    {
      "$id": 49,
      "obj_name": "TXT_blade_info_title",
      "text_id": 216
    },
    {
      "$id": 50,
      "obj_name": "TXT_blade_set_current",
      "text_id": 222
    },
    {
      "$id": 51,
      "obj_name": "TXT_field_skill_title",
      "text_id": 226
    },
    {
      "$id": 52,
      "obj_name": "TXT_fs_item_name@01",
      "text_id": 227
    },
    {
      "$id": 53,
      "obj_name": "TXT_fs_item_lv_title@01",
      "text_id": 228
    },
    {
      "$id": 54,
      "obj_name": "TXT_fs_item_lv_num@01",
      "text_id": 214
    },
    {
      "$id": 55,
      "obj_name": "TXT_fs_item_name@02",
      "text_id": 227
    },
    {
      "$id": 56,
      "obj_name": "TXT_fs_item_lv_title@02",
      "text_id": 228
    },
    {
      "$id": 57,
      "obj_name": "TXT_fs_item_lv_num@02",
      "text_id": 214
    },
    {
      "$id": 58,
      "obj_name": "TXT_fs_item_name@03",
      "text_id": 227
    },
    {
      "$id": 59,
      "obj_name": "TXT_fs_item_lv_title@03",
      "text_id": 228
    },
    {
      "$id": 60,
      "obj_name": "TXT_fs_item_lv_num@03",
      "text_id": 214
    },
    {
      "$id": 61,
      "obj_name": "TXT_fs_item_name@04",
      "text_id": 227
    },
    {
      "$id": 62,
      "obj_name": "TXT_fs_item_lv_title@04",
      "text_id": 228
    },
    {
      "$id": 63,
      "obj_name": "TXT_fs_item_lv_num@04",
      "text_id": 214
    },
    {
      "$id": 64,
      "obj_name": "TXT_fs_item_name@05",
      "text_id": 227
    },
    {
      "$id": 65,
      "obj_name": "TXT_fs_item_lv_title@05",
      "text_id": 228
    },
    {
      "$id": 66,
      "obj_name": "TXT_fs_item_lv_num@05",
      "text_id": 214
    },
    {
      "$id": 67,
      "obj_name": "TXT_fs_item_name@06",
      "text_id": 227
    },
    {
      "$id": 68,
      "obj_name": "TXT_fs_item_lv_title@06",
      "text_id": 228
    },
    {
      "$id": 69,
      "obj_name": "TXT_fs_item_lv_num@06",
      "text_id": 214
    },
    {
      "$id": 70,
      "obj_name": "TXT_fs_item_name@07",
      "text_id": 227
    },
    {
      "$id": 71,
      "obj_name": "TXT_fs_item_lv_title@07",
      "text_id": 228
    },
    {
      "$id": 72,
      "obj_name": "TXT_fs_item_lv_num@07",
      "text_id": 214
    },
    {
      "$id": 73,
      "obj_name": "TXT_fs_item_name@08",
      "text_id": 227
    },
    {
      "$id": 74,
      "obj_name": "TXT_fs_item_lv_title@08",
      "text_id": 228
    },
    {
      "$id": 75,
      "obj_name": "TXT_fs_item_lv_num@08",
      "text_id": 214
    },
    {
      "$id": 76,
      "obj_name": "TXT_fs_item_name@09",
      "text_id": 227
    },
    {
      "$id": 77,
      "obj_name": "TXT_fs_item_lv_title@09",
      "text_id": 228
    },
    {
      "$id": 78,
      "obj_name": "TXT_fs_item_lv_num@09",
      "text_id": 214
    },
    {
      "$id": 79,
      "obj_name": "TXT_fs_item_name@10",
      "text_id": 227
    },
    {
      "$id": 80,
      "obj_name": "TXT_fs_item_lv_title@10",
      "text_id": 228
    },
    {
      "$id": 81,
      "obj_name": "TXT_fs_item_lv_num@10",
      "text_id": 214
    },
    {
      "$id": 82,
      "obj_name": "TXT_fs_item_name@11",
      "text_id": 227
    },
    {
      "$id": 83,
      "obj_name": "TXT_fs_item_lv_title@11",
      "text_id": 228
    },
    {
      "$id": 84,
      "obj_name": "TXT_fs_item_lv_num@11",
      "text_id": 214
    },
    {
      "$id": 85,
      "obj_name": "TXT_fs_item_name@12",
      "text_id": 227
    },
    {
      "$id": 86,
      "obj_name": "TXT_fs_item_lv_title@12",
      "text_id": 228
    },
    {
      "$id": 87,
      "obj_name": "TXT_fs_item_lv_num@12",
      "text_id": 214
    },
    {
      "$id": 88,
      "obj_name": "TXT_fs_item_name@13",
      "text_id": 227
    },
    {
      "$id": 89,
      "obj_name": "TXT_fs_item_lv_title@13",
      "text_id": 228
    },
    {
      "$id": 90,
      "obj_name": "TXT_fs_item_lv_num@13",
      "text_id": 214
    },
    {
      "$id": 91,
      "obj_name": "TXT_fs_item_name@14",
      "text_id": 227
    },
    {
      "$id": 92,
      "obj_name": "TXT_fs_item_lv_title@14",
      "text_id": 228
    },
    {
      "$id": 93,
      "obj_name": "TXT_fs_item_lv_num@14",
      "text_id": 214
    },
    {
      "$id": 94,
      "obj_name": "TXT_fs_item_name@15",
      "text_id": 227
    },
    {
      "$id": 95,
      "obj_name": "TXT_fs_item_lv_title@15",
      "text_id": 228
    },
    {
      "$id": 96,
      "obj_name": "TXT_fs_item_lv_num@15",
      "text_id": 214
    },
    {
      "$id": 97,
      "obj_name": "TXT_fs_page_num",
      "text_id": 233
    },
    {
      "$id": 98,
      "obj_name": "TXT_fs_page_max",
      "text_id": 233
    },
    {
      "$id": 99,
      "obj_name": "TXT_fs_page_slash",
      "text_id": 234
    }
  ]
}