{
  "schema": [
    {
      "name": "name",
      "type": 2
    }
  ],
  "rows": [
    {
      "$id": 1,
      "name": 605
    },
    {
      "$id": 2,
      "name": 606
    },
    {
      "$id": 3,
      "name": 607
    },
    {
      "$id": 4,
      "name": 0
    },
    {
      "$id": 5,
      "name": 0
    },
    {
      "$id": 6,
      "name": 0
    },
    {
      "$id": 7,
      "name": 0
    },
    {
      "$id": 8,
      "name": 0
    },
    {
      "$id": 9,
      "name": 0
    },
    {
      "$id": 10,
      "name": 0
    },
    {
      "$id": 11,
      "name": 326
    },
    {
      "$id": 12,
      "name": 327
    },
    {
      "$id": 13,
      "name": 328
    },
    {
      "$id": 14,
      "name": 445
    },
    {
      "$id": 15,
      "name": 331
    },
    {
      "$id": 16,
      "name": 332
    },
    {
      "$id": 17,
      "name": 365
    },
    {
      "$id": 18,
      "name": 366
    },
    {
      "$id": 19,
      "name": 308
    },
    {
      "$id": 20,
      "name": 309
    }
  ]
}